{"searchresult":{"response":[{"dateTime":"03:57 PM | 01 Aug 2024","bestSellPrice":"6880.95","symbol":"DRREDDY","companytypeLang":"equity","premarket":"false","companyName":"Dr. Reddy's Laboratories Ltd.","openPrice":"6795.50","eventCount":0,"bestBuyQty":1,"companyShortName":"Dr. Reddys","companyName2":"Dr. Reddy's Laboratories Ltd.","bargraphFiftyTwoWeek":"95.57","monthlyPercentageChange":"7.58","companyid":"13841","fiftyTwoWeekHighDateTime":"Jul 26 2024 12:00 AM","fiftyTwoWeekHighPrice":"6966.00","lowPrice":"6786.65","segment":"NSE","highPrice":"6900.50","scripCode":"500124","yearPrice":5583,"lastTradedPrice":"6887.95","value":"318.57","netChange":"137.45","percentChange":"2.04","monthlyNetChange":"485.60","yearlyNetChange":"1304.95","bestSellQty":1,"totalTradedQuantity_Lacs":4.64,"volume":464096,"bargraphvalue":"88.98","yearlyPercentageChange":"23.37","totalTradedValue_Crs":318.57,"fiftyTwoWeekLowDateTime":"Oct 30 2023 12:00 AM","monthPrice":6402.35,"companytype":"equity","scripCode2":"DRREDDY","fiftyTwoWeekLowPrice":"5205.55","nseScripCode":"DRREDDYEQ","closePrice":"6750.50","seoname":"dr-reddys-laboratories-ltd","bestBuyPrice":"6880.80"},{"dateTime":"03:59 PM | 01 Aug 2024","bestSellPrice":"423.75","symbol":"NTPC","companytypeLang":"equity","premarket":"false","companyName":"NTPC Ltd.","openPrice":"419.90","eventCount":0,"bestBuyQty":370,"companyShortName":"NTPC","companyName2":"NTPC Ltd.","bargraphFiftyTwoWeek":"99.58","monthlyPercentageChange":"11.92","companyid":"12316","fiftyTwoWeekHighDateTime":"Aug 01 2024 03:59 PM","fiftyTwoWeekHighPrice":"424.35","lowPrice":"415.60","segment":"NSE","highPrice":"424.35","scripCode":"532555","yearPrice":210,"lastTradedPrice":"423.45","value":"1214.65","netChange":"7.45","percentChange":"1.80","monthlyNetChange":"45.10","yearlyNetChange":"213.45","bestSellQty":601,"totalTradedQuantity_Lacs":288.03,"volume":28803487,"bargraphvalue":"89.71","yearlyPercentageChange":"101.64","totalTradedValue_Crs":1214.65,"fiftyTwoWeekLowDateTime":"Jul 31 2023 12:00 AM","monthPrice":378.35,"companytype":"equity","scripCode2":"NTPC","fiftyTwoWeekLowPrice":"209.65","nseScripCode":"NTPCEQ","closePrice":"416.00","seoname":"ntpc-ltd","bestBuyPrice":"423.55"},{"dateTime":"03:59 PM | 01 Aug 2024","bestSellPrice":"1646.75","symbol":"HDFCBANK","companytypeLang":"equity","premarket":"false","companyName":"HDFC Bank Ltd.","openPrice":"1622.90","eventCount":0,"bestBuyQty":440,"companyShortName":"HDFC Bank","companyName2":"HDFC Bank Ltd.","bargraphFiftyTwoWeek":"63.94","monthlyPercentageChange":"-2.67","companyid":"9195","fiftyTwoWeekHighDateTime":"Jul 03 2024 12:00 AM","fiftyTwoWeekHighPrice":"1794.00","lowPrice":"1617.95","segment":"NSE","highPrice":"1650.05","scripCode":"500180","yearPrice":1643.5,"lastTradedPrice":"1638.80","value":"2139.94","netChange":"23.05","percentChange":"1.43","monthlyNetChange":"-45.00","yearlyNetChange":"-4.70","bestSellQty":117,"totalTradedQuantity_Lacs":131.08,"volume":13107587,"bargraphvalue":"64.95","yearlyPercentageChange":"-0.29","totalTradedValue_Crs":2139.94,"fiftyTwoWeekLowDateTime":"Feb 14 2024 12:00 AM","monthPrice":1683.8,"companytype":"equity","scripCode2":"HDFCBANK","fiftyTwoWeekLowPrice":"1363.55","nseScripCode":"HDFCBANKEQ","closePrice":"1615.75","seoname":"hdfc-bank-ltd","bestBuyPrice":"1646.65"},{"dateTime":"03:59 PM | 01 Aug 2024","bestSellPrice":"642.95","symbol":"DABUR","companytypeLang":"equity","premarket":"false","companyName":"Dabur India Ltd.","openPrice":"638.90","eventCount":0,"bestBuyQty":6,"companyShortName":"Dabur India","companyName2":"Dabur India Ltd.","bargraphFiftyTwoWeek":"89.11","monthlyPercentageChange":"7.13","companyid":"11796","fiftyTwoWeekHighDateTime":"Jul 23 2024 12:00 AM","fiftyTwoWeekHighPrice":"662.35","lowPrice":"636.75","segment":"NSE","highPrice":"655.85","scripCode":"500096","yearPrice":581.7,"lastTradedPrice":"643.50","value":"441.40","netChange":"7.80","percentChange":"1.23","monthlyNetChange":"42.80","yearlyNetChange":"61.80","bestSellQty":592,"totalTradedQuantity_Lacs":68.53,"volume":6852547,"bargraphvalue":"35.34","yearlyPercentageChange":"10.62","totalTradedValue_Crs":441.4,"fiftyTwoWeekLowDateTime":"Apr 15 2024 12:00 AM","monthPrice":600.7,"companytype":"equity","scripCode2":"DABUR","fiftyTwoWeekLowPrice":"489.20","nseScripCode":"DABUREQ","closePrice":"635.70","seoname":"dabur-india-ltd","bestBuyPrice":"642.90"},{"dateTime":"03:58 PM | 01 Aug 2024","bestSellPrice":"2484.90","symbol":"NESTLEIND","companytypeLang":"equity","premarket":"false","companyName":"Nestle India Ltd.","openPrice":"2465.00","eventCount":0,"bestBuyQty":20,"companyShortName":"Nestle India","companyName2":"Nestle India Ltd.","bargraphFiftyTwoWeek":"54.30","monthlyPercentageChange":"-2.65","companyid":"13330","fiftyTwoWeekHighDateTime":"Jan 02 2024 12:00 AM","fiftyTwoWeekHighPrice":"2769.30","lowPrice":"2456.35","segment":"NSE","highPrice":"2492.30","scripCode":"500790","yearPrice":2248.09,"lastTradedPrice":"2484.00","value":"329.23","netChange":"27.66","percentChange":"1.13","monthlyNetChange":"-67.65","yearlyNetChange":"235.91","bestSellQty":100,"totalTradedQuantity_Lacs":13.27,"volume":1326762,"bargraphvalue":"76.91","yearlyPercentageChange":"10.49","totalTradedValue_Crs":329.23,"fiftyTwoWeekLowDateTime":"Aug 18 2023 12:00 AM","monthPrice":2551.65,"companytype":"equity","scripCode2":"NESTLEIND","fiftyTwoWeekLowPrice":"2145.00","nseScripCode":"NESTLEINDEQ","closePrice":"2456.35","seoname":"nestle-india-ltd","bestBuyPrice":"2484.50"},{"dateTime":"03:54 PM | 01 Aug 2024","bestSellPrice":"3248.85","symbol":"TORNTPHARM","companytypeLang":"equity","premarket":"false","companyName":"Torrent Pharmaceuticals Ltd.","openPrice":"3172.05","eventCount":0,"bestBuyQty":137,"companyShortName":"Torrent Pharma","companyName2":"Torrent Pharmaceuticals Ltd.","bargraphFiftyTwoWeek":"96.49","monthlyPercentageChange":"14.82","companyid":"8492","fiftyTwoWeekHighDateTime":"Jul 26 2024 12:00 AM","fiftyTwoWeekHighPrice":"3257.15","lowPrice":"3160.05","segment":"NSE","highPrice":"3256.35","scripCode":"500420","yearPrice":1990.3,"lastTradedPrice":"3205.00","value":"128.09","netChange":"33.25","percentChange":"1.05","monthlyNetChange":"413.70","yearlyNetChange":"1214.70","bestSellQty":2,"totalTradedQuantity_Lacs":4.01,"volume":400745,"bargraphvalue":"46.68","yearlyPercentageChange":"61.03","totalTradedValue_Crs":128.09,"fiftyTwoWeekLowDateTime":"Sep 01 2023 12:00 AM","monthPrice":2791.3,"companytype":"equity","scripCode2":"TORNTPHARM","fiftyTwoWeekLowPrice":"1772.05","nseScripCode":"TORNTPHARMEQ","closePrice":"3171.75","seoname":"torrent-pharmaceuticals-ltd","bestBuyPrice":"3243.10"},{"dateTime":"03:59 PM | 01 Aug 2024","bestSellPrice":"1502.50","symbol":"BHARTIARTL","companytypeLang":"equity","premarket":"false","companyName":"Bharti Airtel Ltd.","openPrice":"1485.00","eventCount":0,"bestBuyQty":300,"companyShortName":"Bharti Airtel","companyName2":"Bharti Airtel Ltd.","bargraphFiftyTwoWeek":"95.54","monthlyPercentageChange":"4.26","companyid":"2718","fiftyTwoWeekHighDateTime":"Jun 28 2024 12:00 AM","fiftyTwoWeekHighPrice":"1536.25","lowPrice":"1485.00","segment":"NSE","highPrice":"1511.00","scripCode":"532454","yearPrice":895.1,"lastTradedPrice":"1505.50","value":"681.70","netChange":"13.96","percentChange":"0.94","monthlyNetChange":"61.45","yearlyNetChange":"610.40","bestSellQty":12,"totalTradedQuantity_Lacs":45.31,"volume":4531379,"bargraphvalue":"78.85","yearlyPercentageChange":"68.19","totalTradedValue_Crs":681.7,"fiftyTwoWeekLowDateTime":"Aug 31 2023 12:00 AM","monthPrice":1444.05,"companytype":"equity","scripCode2":"BHARTIARTL","fiftyTwoWeekLowPrice":"847.05","nseScripCode":"BHARTIARTLEQ","closePrice":"1491.55","seoname":"bharti-airtel-ltd","bestBuyPrice":"1502.10"},{"dateTime":"03:55 PM | 01 Aug 2024","bestSellPrice":"11964.55","symbol":"ULTRACEMCO","companytypeLang":"equity","premarket":"false","companyName":"UltraTech Cement Ltd.","openPrice":"11887.20","eventCount":0,"bestBuyQty":100,"companyShortName":"UltraTech Cem.","companyName2":"UltraTech Cement Ltd.","bargraphFiftyTwoWeek":"97.71","monthlyPercentageChange":"2.71","companyid":"3027","fiftyTwoWeekHighDateTime":"Jul 02 2024 12:00 AM","fiftyTwoWeekHighPrice":"12078.00","lowPrice":"11803.50","segment":"NSE","highPrice":"12032.30","scripCode":"532538","yearPrice":8306.75,"lastTradedPrice":"11984.50","value":"297.60","netChange":"97.30","percentChange":"0.82","monthlyNetChange":"316.60","yearlyNetChange":"3677.75","bestSellQty":1,"totalTradedQuantity_Lacs":2.5,"volume":250126,"bargraphvalue":"79.11","yearlyPercentageChange":"44.27","totalTradedValue_Crs":297.6,"fiftyTwoWeekLowDateTime":"Aug 16 2023 12:00 AM","monthPrice":11667.9,"companytype":"equity","scripCode2":"ULTRACEMCO","fiftyTwoWeekLowPrice":"7987.65","nseScripCode":"ULTRACEMCOEQ","closePrice":"11887.20","seoname":"ultratech-cement-ltd","bestBuyPrice":"11957.80"},{"dateTime":"03:59 PM | 01 Aug 2024","bestSellPrice":"1765.50","symbol":"SBILIFE","companytypeLang":"equity","premarket":"false","companyName":"SBI Life Insurance Company Ltd.","openPrice":"1791.10","eventCount":0,"bestBuyQty":61,"companyShortName":"SBI Life","companyName2":"SBI Life Insurance Company Ltd.","bargraphFiftyTwoWeek":"95.57","monthlyPercentageChange":"18.45","companyid":"2898","fiftyTwoWeekHighDateTime":"Aug 01 2024 03:59 PM","fiftyTwoWeekHighPrice":"1791.15","lowPrice":"1758.10","segment":"NSE","highPrice":"1791.15","scripCode":"540719","yearPrice":1289.75,"lastTradedPrice":"1767.25","value":"220.88","netChange":"13.60","percentChange":"0.78","monthlyNetChange":"275.30","yearlyNetChange":"477.50","bestSellQty":51,"totalTradedQuantity_Lacs":12.47,"volume":1247361,"bargraphvalue":"27.69","yearlyPercentageChange":"37.02","totalTradedValue_Crs":220.88,"fiftyTwoWeekLowDateTime":"Aug 03 2023 12:00 AM","monthPrice":1491.95,"companytype":"equity","scripCode2":"SBILIFE","fiftyTwoWeekLowPrice":"1251.65","nseScripCode":"SBILIFEEQ","closePrice":"1753.65","seoname":"sbi-life-insurance-company-ltd","bestBuyPrice":"1765.45"},{"dateTime":"03:59 PM | 01 Aug 2024","bestSellPrice":"9742.00","symbol":"BAJAJ-AUTO","companytypeLang":"equity","premarket":"false","companyName":"Bajaj Auto Ltd.","openPrice":"9844.00","eventCount":0,"bestBuyQty":20,"companyShortName":"Bajaj Auto","companyName2":"Bajaj Auto Ltd.","bargraphFiftyTwoWeek":"94.39","monthlyPercentageChange":"2.41","companyid":"21430","fiftyTwoWeekHighDateTime":"Jun 18 2024 12:00 AM","fiftyTwoWeekHighPrice":"10038.80","lowPrice":"9662.00","segment":"NSE","highPrice":"9844.00","scripCode":"532977","yearPrice":4892.5,"lastTradedPrice":"9730.50","value":"300.19","netChange":"66.30","percentChange":"0.69","monthlyNetChange":"228.85","yearlyNetChange":"4838.00","bestSellQty":5,"totalTradedQuantity_Lacs":3.09,"volume":308658,"bargraphvalue":"37.64","yearlyPercentageChange":"98.89","totalTradedValue_Crs":300.19,"fiftyTwoWeekLowDateTime":"Aug 14 2023 12:00 AM","monthPrice":9501.65,"companytype":"equity","scripCode2":"BAJAJ-AUTO","fiftyTwoWeekLowPrice":"4541.00","nseScripCode":"BAJAJ-AUTOEQ","closePrice":"9664.20","seoname":"bajaj-auto-ltd","bestBuyPrice":"9741.00"},{"dateTime":"03:59 PM | 01 Aug 2024","bestSellPrice":"3033.50","symbol":"RELIANCE","companytypeLang":"equity","premarket":"false","companyName":"Reliance Industries Ltd.","openPrice":"3024.00","eventCount":0,"bestBuyQty":21,"companyShortName":"RIL","companyName2":"Reliance Industries Ltd.","bargraphFiftyTwoWeek":"81.25","monthlyPercentageChange":"-3.20","companyid":"13215","fiftyTwoWeekHighDateTime":"Jul 08 2024 12:00 AM","fiftyTwoWeekHighPrice":"3217.60","lowPrice":"3008.60","segment":"NSE","highPrice":"3036.00","scripCode":"500325","yearPrice":2527.85,"lastTradedPrice":"3030.60","value":"1628.36","netChange":"19.75","percentChange":"0.66","monthlyNetChange":"-100.20","yearlyNetChange":"502.75","bestSellQty":70,"totalTradedQuantity_Lacs":53.82,"volume":5382111,"bargraphvalue":"80.29","yearlyPercentageChange":"19.89","totalTradedValue_Crs":1628.36,"fiftyTwoWeekLowDateTime":"Oct 26 2023 12:00 AM","monthPrice":3130.8,"companytype":"equity","scripCode2":"RELIANCE","fiftyTwoWeekLowPrice":"2220.30","nseScripCode":"RELIANCEEQ","closePrice":"3010.85","seoname":"reliance-industries-ltd","bestBuyPrice":"3033.20"},{"dateTime":"03:59 PM | 01 Aug 2024","bestSellPrice":"3092.25","symbol":"ASIANPAINT","companytypeLang":"equity","premarket":"false","companyName":"Asian Paints Ltd.","openPrice":"3088.00","eventCount":0,"bestBuyQty":21,"companyShortName":"Asian Paints","companyName2":"Asian Paints Ltd.","bargraphFiftyTwoWeek":"57.02","monthlyPercentageChange":"6.25","companyid":"14034","fiftyTwoWeekHighDateTime":"Dec 29 2023 12:00 AM","fiftyTwoWeekHighPrice":"3422.95","lowPrice":"3062.80","segment":"NSE","highPrice":"3128.95","scripCode":"500820","yearPrice":3390.7,"lastTradedPrice":"3099.35","value":"519.00","netChange":"14.91","percentChange":"0.49","monthlyNetChange":"182.30","yearlyNetChange":"-291.35","bestSellQty":23,"totalTradedQuantity_Lacs":16.75,"volume":1675122,"bargraphvalue":"55.25","yearlyPercentageChange":"-8.59","totalTradedValue_Crs":519,"fiftyTwoWeekLowDateTime":"May 10 2024 12:00 AM","monthPrice":2917.05,"companytype":"equity","scripCode2":"ASIANPAINT","fiftyTwoWeekLowPrice":"2670.10","nseScripCode":"ASIANPAINTEQ","closePrice":"3084.45","seoname":"asian-paints-ltd","bestBuyPrice":"3091.55"},{"dateTime":"03:59 PM | 01 Aug 2024","bestSellPrice":"2715.90","symbol":"HINDUNILVR","companytypeLang":"equity","premarket":"false","companyName":"Hindustan Unilever Ltd.","openPrice":"2714.00","eventCount":0,"bestBuyQty":100,"companyShortName":"HUL","companyName2":"Hindustan Unilever Ltd.","bargraphFiftyTwoWeek":"85.02","monthlyPercentageChange":"9.81","companyid":"13616","fiftyTwoWeekHighDateTime":"Jul 23 2024 12:00 AM","fiftyTwoWeekHighPrice":"2811.30","lowPrice":"2695.20","segment":"NSE","highPrice":"2724.95","scripCode":"500696","yearPrice":2584.6,"lastTradedPrice":"2715.55","value":"511.12","netChange":"9.91","percentChange":"0.37","monthlyNetChange":"242.50","yearlyNetChange":"130.95","bestSellQty":148,"totalTradedQuantity_Lacs":18.86,"volume":1886392,"bargraphvalue":"68.40","yearlyPercentageChange":"5.07","totalTradedValue_Crs":511.12,"fiftyTwoWeekLowDateTime":"Apr 16 2024 12:00 AM","monthPrice":2473.05,"companytype":"equity","scripCode2":"HINDUNILVR","fiftyTwoWeekLowPrice":"2172.05","nseScripCode":"HINDUNILVREQ","closePrice":"2705.65","seoname":"hindustan-unilever-ltd","bestBuyPrice":"2715.50"},{"dateTime":"03:59 PM | 01 Aug 2024","bestSellPrice":"3469.00","symbol":"TITAN","companytypeLang":"equity","premarket":"false","companyName":"Titan Company Ltd.","openPrice":"3475.00","eventCount":0,"bestBuyQty":1,"companyShortName":"Titan Company ","companyName2":"Titan Company Ltd.","bargraphFiftyTwoWeek":"58.33","monthlyPercentageChange":"1.88","companyid":"12903","fiftyTwoWeekHighDateTime":"Jan 30 2024 12:00 AM","fiftyTwoWeekHighPrice":"3886.95","lowPrice":"3442.50","segment":"NSE","highPrice":"3492.00","scripCode":"500114","yearPrice":2987,"lastTradedPrice":"3468.35","value":"305.21","netChange":"9.41","percentChange":"0.28","monthlyNetChange":"64.15","yearlyNetChange":"481.35","bestSellQty":2,"totalTradedQuantity_Lacs":8.79,"volume":879399,"bargraphvalue":"52.22","yearlyPercentageChange":"16.11","totalTradedValue_Crs":305.21,"fiftyTwoWeekLowDateTime":"Aug 07 2023 12:00 AM","monthPrice":3404.2,"companytype":"equity","scripCode2":"TITAN","fiftyTwoWeekLowPrice":"2882.45","nseScripCode":"TITANEQ","closePrice":"3458.95","seoname":"titan-company-ltd","bestBuyPrice":"3467.55"},{"dateTime":"03:59 PM | 01 Aug 2024","bestSellPrice":"4384.00","symbol":"TCS","companytypeLang":"equity","premarket":"false","companyName":"Tata Consultancy Services Ltd.","openPrice":"4399.40","eventCount":0,"bestBuyQty":113,"companyShortName":"TCS","companyName2":"Tata Consultancy Services Ltd.","bargraphFiftyTwoWeek":"96.97","monthlyPercentageChange":"12.63","companyid":"8345","fiftyTwoWeekHighDateTime":"Jul 29 2024 12:00 AM","fiftyTwoWeekHighPrice":"4431.00","lowPrice":"4365.05","segment":"NSE","highPrice":"4419.30","scripCode":"532540","yearPrice":3355.4,"lastTradedPrice":"4397.10","value":"966.80","netChange":"11.75","percentChange":"0.27","monthlyNetChange":"492.95","yearlyNetChange":"1041.70","bestSellQty":10,"totalTradedQuantity_Lacs":22.02,"volume":2202244,"bargraphvalue":"59.08","yearlyPercentageChange":"31.05","totalTradedValue_Crs":966.8,"fiftyTwoWeekLowDateTime":"Nov 01 2023 12:00 AM","monthPrice":3904.15,"companytype":"equity","scripCode2":"TCS","fiftyTwoWeekLowPrice":"3311.00","nseScripCode":"TCSEQ","closePrice":"4385.35","seoname":"tata-consultancy-services-ltd","bestBuyPrice":"4382.85"},{"dateTime":"03:59 PM | 01 Aug 2024","bestSellPrice":"1545.30","symbol":"CIPLA","companytypeLang":"equity","premarket":"false","companyName":"Cipla Ltd.","openPrice":"1545.95","eventCount":0,"bestBuyQty":1,"companyShortName":"Cipla","companyName2":"Cipla Ltd.","bargraphFiftyTwoWeek":"88.50","monthlyPercentageChange":"4.42","companyid":"13917","fiftyTwoWeekHighDateTime":"Jul 26 2024 12:00 AM","fiftyTwoWeekHighPrice":"1600.00","lowPrice":"1535.55","segment":"NSE","highPrice":"1552.50","scripCode":"500087","yearPrice":1177.8,"lastTradedPrice":"1546.20","value":"236.06","netChange":"1.91","percentChange":"0.13","monthlyNetChange":"65.40","yearlyNetChange":"368.40","bestSellQty":27,"totalTradedQuantity_Lacs":15.29,"volume":1529481,"bargraphvalue":"62.83","yearlyPercentageChange":"31.28","totalTradedValue_Crs":236.06,"fiftyTwoWeekLowDateTime":"Oct 26 2023 12:00 AM","monthPrice":1480.8,"companytype":"equity","scripCode2":"CIPLA","fiftyTwoWeekLowPrice":"1132.00","nseScripCode":"CIPLAEQ","closePrice":"1544.30","seoname":"cipla-ltd","bestBuyPrice":"1544.95"},{"dateTime":"03:55 PM | 01 Aug 2024","bestSellPrice":"675.15","symbol":"MARICO","companytypeLang":"equity","premarket":"false","companyName":"Marico Ltd.","openPrice":"675.65","eventCount":0,"bestBuyQty":52,"companyShortName":"Marico","companyName2":"Marico Ltd.","bargraphFiftyTwoWeek":"92.13","monthlyPercentageChange":"10.10","companyid":"5886","fiftyTwoWeekHighDateTime":"Jul 30 2024 12:00 AM","fiftyTwoWeekHighPrice":"691.00","lowPrice":"670.60","segment":"NSE","highPrice":"681.45","scripCode":"531642","yearPrice":574.35,"lastTradedPrice":"674.90","value":"77.69","netChange":"0.80","percentChange":"0.12","monthlyNetChange":"61.90","yearlyNetChange":"100.55","bestSellQty":519,"totalTradedQuantity_Lacs":11.49,"volume":1148693,"bargraphvalue":"39.63","yearlyPercentageChange":"17.51","totalTradedValue_Crs":77.69,"fiftyTwoWeekLowDateTime":"Mar 19 2024 12:00 AM","monthPrice":613,"companytype":"equity","scripCode2":"MARICO","fiftyTwoWeekLowPrice":"486.30","nseScripCode":"MARICOEQ","closePrice":"674.10","seoname":"marico-ltd","bestBuyPrice":"674.90"},{"dateTime":"03:59 PM | 01 Aug 2024","bestSellPrice":"521.05","symbol":"WIPRO","companytypeLang":"equity","premarket":"false","companyName":"Wipro Ltd.","openPrice":"523.00","eventCount":0,"bestBuyQty":94,"companyShortName":"Wipro","companyName2":"Wipro Ltd.","bargraphFiftyTwoWeek":"71.52","monthlyPercentageChange":"1.30","companyid":"12799","fiftyTwoWeekHighDateTime":"Jul 19 2024 12:00 AM","fiftyTwoWeekHighPrice":"579.90","lowPrice":"517.50","segment":"NSE","highPrice":"526.80","scripCode":"507685","yearPrice":398.75,"lastTradedPrice":"521.55","value":"280.94","netChange":"-0.46","percentChange":"-0.09","monthlyNetChange":"6.70","yearlyNetChange":"122.80","bestSellQty":70,"totalTradedQuantity_Lacs":53.8,"volume":5379876,"bargraphvalue":"43.55","yearlyPercentageChange":"30.80","totalTradedValue_Crs":280.94,"fiftyTwoWeekLowDateTime":"Oct 26 2023 12:00 AM","monthPrice":514.85,"companytype":"equity","scripCode2":"WIPRO","fiftyTwoWeekLowPrice":"375.05","nseScripCode":"WIPROEQ","closePrice":"522.00","seoname":"wipro-ltd","bestBuyPrice":"520.80"},{"dateTime":"03:59 PM | 01 Aug 2024","bestSellPrice":"1639.55","symbol":"HCLTECH","companytypeLang":"equity","premarket":"false","companyName":"HCL Technologies Ltd.","openPrice":"1640.05","eventCount":0,"bestBuyQty":583,"companyShortName":"HCL Tech","companyName2":"HCL Technologies Ltd.","bargraphFiftyTwoWeek":"90.55","monthlyPercentageChange":"12.40","companyid":"4291","fiftyTwoWeekHighDateTime":"Feb 23 2024 12:00 AM","fiftyTwoWeekHighPrice":"1697.35","lowPrice":"1636.10","segment":"NSE","highPrice":"1655.50","scripCode":"532281","yearPrice":1103.55,"lastTradedPrice":"1640.55","value":"293.42","netChange":"-2.05","percentChange":"-0.13","monthlyNetChange":"180.95","yearlyNetChange":"537.00","bestSellQty":17,"totalTradedQuantity_Lacs":17.85,"volume":1785188,"bargraphvalue":"22.94","yearlyPercentageChange":"48.66","totalTradedValue_Crs":293.42,"fiftyTwoWeekLowDateTime":"Jul 31 2023 12:00 AM","monthPrice":1459.6,"companytype":"equity","scripCode2":"HCLTECH","fiftyTwoWeekLowPrice":"1096.00","nseScripCode":"HCLTECHEQ","closePrice":"1642.60","seoname":"hcl-technologies-ltd","bestBuyPrice":"1639.50"},{"dateTime":"03:57 PM | 01 Aug 2024","bestSellPrice":"1710.50","symbol":"SUNPHARMA","companytypeLang":"equity","premarket":"false","companyName":"Sun Pharmaceutical Industries Ltd.","openPrice":"1725.50","eventCount":0,"bestBuyQty":11,"companyShortName":"Sun Pharma","companyName2":"Sun Pharmaceutical Industries Ltd.","bargraphFiftyTwoWeek":"95.39","monthlyPercentageChange":"12.78","companyid":"9134","fiftyTwoWeekHighDateTime":"Aug 01 2024 03:57 PM","fiftyTwoWeekHighPrice":"1746.45","lowPrice":"1681.30","segment":"NSE","highPrice":"1746.45","scripCode":"524715","yearPrice":1138.55,"lastTradedPrice":"1715.20","value":"903.08","netChange":"-4.15","percentChange":"-0.25","monthlyNetChange":"194.35","yearlyNetChange":"576.65","bestSellQty":159,"totalTradedQuantity_Lacs":52.58,"volume":5258291,"bargraphvalue":"52.03","yearlyPercentageChange":"50.65","totalTradedValue_Crs":903.08,"fiftyTwoWeekLowDateTime":"Oct 31 2023 12:00 AM","monthPrice":1520.85,"companytype":"equity","scripCode2":"SUNPHARMA","fiftyTwoWeekLowPrice":"1068.35","nseScripCode":"SUNPHARMAEQ","closePrice":"1719.35","seoname":"sun-pharmaceutical-industries-ltd","bestBuyPrice":"1710.35"},{"dateTime":"03:59 PM | 01 Aug 2024","bestSellPrice":"493.95","symbol":"ITC","companytypeLang":"equity","premarket":"false","companyName":"ITC Ltd.","openPrice":"495.95","eventCount":0,"bestBuyQty":3819,"companyShortName":"ITC","companyName2":"ITC Ltd.","bargraphFiftyTwoWeek":"84.77","monthlyPercentageChange":"16.19","companyid":"13554","fiftyTwoWeekHighDateTime":"Jul 24 2024 12:00 AM","fiftyTwoWeekHighPrice":"510.65","lowPrice":"490.95","segment":"NSE","highPrice":"496.75","scripCode":"500875","yearPrice":468.45,"lastTradedPrice":"493.70","value":"575.96","netChange":"-1.66","percentChange":"-0.34","monthlyNetChange":"68.80","yearlyNetChange":"25.25","bestSellQty":976,"totalTradedQuantity_Lacs":116.66,"volume":11665529,"bargraphvalue":"47.41","yearlyPercentageChange":"5.39","totalTradedValue_Crs":575.96,"fiftyTwoWeekLowDateTime":"Mar 12 2024 12:00 AM","monthPrice":424.9,"companytype":"equity","scripCode2":"ITC","fiftyTwoWeekLowPrice":"399.35","nseScripCode":"ITCEQ","closePrice":"495.35","seoname":"itc-ltd","bestBuyPrice":"493.90"},{"dateTime":"03:59 PM | 01 Aug 2024","bestSellPrice":"553.00","symbol":"BERGEPAINT","companytypeLang":"equity","premarket":"false","companyName":"Berger Paints (India) Ltd.","openPrice":"553.85","eventCount":0,"bestBuyQty":36,"companyShortName":"Berger Paints","companyName2":"Berger Paints (India) Ltd.","bargraphFiftyTwoWeek":"47.35","monthlyPercentageChange":"9.68","companyid":"13971","fiftyTwoWeekHighDateTime":"Sep 22 2023 12:00 AM","fiftyTwoWeekHighPrice":"679.75","lowPrice":"547.70","segment":"NSE","highPrice":"558.00","scripCode":"509480","yearPrice":566.38,"lastTradedPrice":"553.00","value":"41.58","netChange":"-1.90","percentChange":"-0.35","monthlyNetChange":"48.80","yearlyNetChange":"-13.38","bestSellQty":213,"totalTradedQuantity_Lacs":7.53,"volume":752570,"bargraphvalue":"51.46","yearlyPercentageChange":"-2.36","totalTradedValue_Crs":41.58,"fiftyTwoWeekLowDateTime":"Jun 04 2024 12:00 AM","monthPrice":504.2,"companytype":"equity","scripCode2":"BERGEPAINT","fiftyTwoWeekLowPrice":"439.00","nseScripCode":"BERGEPAINTEQ","closePrice":"554.90","seoname":"berger-paints-india-ltd","bestBuyPrice":"552.80"},{"dateTime":"03:59 PM | 01 Aug 2024","bestSellPrice":"1208.85","symbol":"ICICIBANK","companytypeLang":"equity","premarket":"false","companyName":"ICICI Bank Ltd.","openPrice":"1212.50","eventCount":0,"bestBuyQty":91,"companyShortName":"ICICI Bank","companyName2":"ICICI Bank Ltd.","bargraphFiftyTwoWeek":"86.71","monthlyPercentageChange":"0.88","companyid":"9194","fiftyTwoWeekHighDateTime":"Jul 11 2024 12:00 AM","fiftyTwoWeekHighPrice":"1257.80","lowPrice":"1206.90","segment":"NSE","highPrice":"1222.65","scripCode":"532174","yearPrice":996.2,"lastTradedPrice":"1210.10","value":"1058.54","netChange":"-4.81","percentChange":"-0.40","monthlyNetChange":"10.50","yearlyNetChange":"213.90","bestSellQty":62,"totalTradedQuantity_Lacs":87.25,"volume":8725046,"bargraphvalue":"20.32","yearlyPercentageChange":"21.47","totalTradedValue_Crs":1058.54,"fiftyTwoWeekLowDateTime":"Oct 26 2023 12:00 AM","monthPrice":1199.6,"companytype":"equity","scripCode2":"ICICIBANK","fiftyTwoWeekLowPrice":"899.00","nseScripCode":"ICICIBANKEQ","closePrice":"1214.90","seoname":"icici-bank-ltd","bestBuyPrice":"1208.50"},{"dateTime":"03:59 PM | 01 Aug 2024","bestSellPrice":"1791.00","symbol":"KOTAKBANK","companytypeLang":"equity","premarket":"false","companyName":"Kotak Mahindra Bank Ltd.","openPrice":"1807.10","eventCount":0,"bestBuyQty":23,"companyShortName":"Kotak Bank","companyName2":"Kotak Mahindra Bank Ltd.","bargraphFiftyTwoWeek":"65.02","monthlyPercentageChange":"-0.55","companyid":"12161","fiftyTwoWeekHighDateTime":"Dec 28 2023 12:00 AM","fiftyTwoWeekHighPrice":"1926.50","lowPrice":"1786.25","segment":"NSE","highPrice":"1818.25","scripCode":"500247","yearPrice":1876.85,"lastTradedPrice":"1792.65","value":"685.07","netChange":"-15.25","percentChange":"-0.85","monthlyNetChange":"-9.85","yearlyNetChange":"-84.20","bestSellQty":556,"totalTradedQuantity_Lacs":38.16,"volume":3816044,"bargraphvalue":"20.00","yearlyPercentageChange":"-4.49","totalTradedValue_Crs":685.07,"fiftyTwoWeekLowDateTime":"May 03 2024 12:00 AM","monthPrice":1802.5,"companytype":"equity","scripCode2":"KOTAKBANK","fiftyTwoWeekLowPrice":"1543.85","nseScripCode":"KOTAKBANKEQ","closePrice":"1807.90","seoname":"kotak-mahindra-bank-ltd","bestBuyPrice":"1790.20"},{"dateTime":"03:57 PM | 01 Aug 2024","bestSellPrice":"5723.60","symbol":"BRITANNIA","companytypeLang":"equity","premarket":"false","companyName":"Britannia Industries Ltd.","openPrice":"5784.45","eventCount":0,"bestBuyQty":34,"companyShortName":"Britannia","companyName2":"Britannia Industries Ltd.","bargraphFiftyTwoWeek":"83.42","monthlyPercentageChange":"4.65","companyid":"13934","fiftyTwoWeekHighDateTime":"Jul 23 2024 12:00 AM","fiftyTwoWeekHighPrice":"6005.00","lowPrice":"5700.00","segment":"NSE","highPrice":"5839.90","scripCode":"500825","yearPrice":4903.35,"lastTradedPrice":"5730.15","value":"175.44","netChange":"-54.31","percentChange":"-0.94","monthlyNetChange":"254.60","yearlyNetChange":"826.80","bestSellQty":1,"totalTradedQuantity_Lacs":3.04,"volume":304411,"bargraphvalue":"21.55","yearlyPercentageChange":"16.86","totalTradedValue_Crs":175.44,"fiftyTwoWeekLowDateTime":"Nov 01 2023 12:00 AM","monthPrice":5475.55,"companytype":"equity","scripCode2":"BRITANNIA","fiftyTwoWeekLowPrice":"4347.70","nseScripCode":"BRITANNIAEQ","closePrice":"5784.45","seoname":"britannia-industries-ltd","bestBuyPrice":"5723.00"},{"dateTime":"03:59 PM | 01 Aug 2024","bestSellPrice":"3771.30","symbol":"LT","companytypeLang":"equity","premarket":"false","companyName":"Larsen & Toubro Ltd.","openPrice":"3810.00","eventCount":0,"bestBuyQty":49,"companyShortName":"L&T","companyName2":"Larsen & Toubro Ltd.","bargraphFiftyTwoWeek":"89.46","monthlyPercentageChange":"6.51","companyid":"13447","fiftyTwoWeekHighDateTime":"Jun 03 2024 12:00 AM","fiftyTwoWeekHighPrice":"3919.90","lowPrice":"3765.85","segment":"NSE","highPrice":"3838.95","scripCode":"500510","yearPrice":2649.55,"lastTradedPrice":"3779.30","value":"758.58","netChange":"-35.70","percentChange":"-0.94","monthlyNetChange":"230.85","yearlyNetChange":"1129.75","bestSellQty":57,"totalTradedQuantity_Lacs":19.99,"volume":1998663,"bargraphvalue":"18.40","yearlyPercentageChange":"42.64","totalTradedValue_Crs":758.58,"fiftyTwoWeekLowDateTime":"Aug 03 2023 12:00 AM","monthPrice":3548.45,"companytype":"equity","scripCode2":"LT","fiftyTwoWeekLowPrice":"2586.30","nseScripCode":"LTEQ","closePrice":"3815.00","seoname":"larsen-toubro-ltd","bestBuyPrice":"3771.05"},{"dateTime":"03:59 PM | 01 Aug 2024","bestSellPrice":"3373.50","symbol":"COLPAL","companytypeLang":"equity","premarket":"false","companyName":"Colgate-Palmolive (India) Ltd.","openPrice":"3350.40","eventCount":0,"bestBuyQty":58,"companyShortName":"Colgate-Palmolive","companyName2":"Colgate-Palmolive (India) Ltd.","bargraphFiftyTwoWeek":"96.65","monthlyPercentageChange":"18.68","companyid":"13873","fiftyTwoWeekHighDateTime":"Jul 30 2024 12:00 AM","fiftyTwoWeekHighPrice":"3424.95","lowPrice":"3350.40","segment":"NSE","highPrice":"3408.95","scripCode":"500830","yearPrice":2049.3,"lastTradedPrice":"3374.20","value":"220.50","netChange":"-37.91","percentChange":"-1.12","monthlyNetChange":"531.05","yearlyNetChange":"1324.90","bestSellQty":3,"totalTradedQuantity_Lacs":6.54,"volume":653964,"bargraphvalue":"40.65","yearlyPercentageChange":"64.65","totalTradedValue_Crs":220.5,"fiftyTwoWeekLowDateTime":"Aug 22 2023 12:00 AM","monthPrice":2843.15,"companytype":"equity","scripCode2":"COLPAL","fiftyTwoWeekLowPrice":"1909.00","nseScripCode":"COLPALEQ","closePrice":"3412.10","seoname":"colgate-palmolive-india-ltd","bestBuyPrice":"3370.45"},{"dateTime":"03:46 PM | 01 Aug 2024","bestSellPrice":"34309.90","symbol":"BOSCHLTD","companytypeLang":"equity","premarket":"false","companyName":"Bosch Ltd.","openPrice":"34853.00","eventCount":0,"bestBuyQty":15,"companyShortName":"Bosch","companyName2":"Bosch Ltd.","bargraphFiftyTwoWeek":"87.69","monthlyPercentageChange":"0.84","companyid":"11911","fiftyTwoWeekHighDateTime":"Jun 27 2024 12:00 AM","fiftyTwoWeekHighPrice":"36678.00","lowPrice":"34266.10","segment":"NSE","highPrice":"35182.80","scripCode":"500530","yearPrice":18952.85,"lastTradedPrice":"34370.70","value":"80.27","netChange":"-607.75","percentChange":"-1.74","monthlyNetChange":"286.30","yearlyNetChange":"15417.85","bestSellQty":10,"totalTradedQuantity_Lacs":0.23,"volume":23238,"bargraphvalue":"11.41","yearlyPercentageChange":"81.35","totalTradedValue_Crs":80.27,"fiftyTwoWeekLowDateTime":"Aug 14 2023 12:00 AM","monthPrice":34084.4,"companytype":"equity","scripCode2":"BOSCHLTD","fiftyTwoWeekLowPrice":"17931.15","nseScripCode":"BOSCHLTDEQ","closePrice":"34978.45","seoname":"bosch-ltd","bestBuyPrice":"34300.00"},{"dateTime":"03:59 PM | 01 Aug 2024","bestSellPrice":"3132.40","symbol":"PIDILITIND","companytypeLang":"equity","premarket":"false","companyName":"Pidilite Industries Ltd.","openPrice":"3192.05","eventCount":0,"bestBuyQty":1,"companyShortName":"Pidilite Ind","companyName2":"Pidilite Industries Ltd.","bargraphFiftyTwoWeek":"87.19","monthlyPercentageChange":"-1.19","companyid":"10460","fiftyTwoWeekHighDateTime":"Jul 19 2024 12:00 AM","fiftyTwoWeekHighPrice":"3243.05","lowPrice":"3115.25","segment":"NSE","highPrice":"3206.85","scripCode":"500331","yearPrice":2615.85,"lastTradedPrice":"3121.30","value":"70.09","netChange":"-65.10","percentChange":"-2.05","monthlyNetChange":"-37.65","yearlyNetChange":"505.45","bestSellQty":1,"totalTradedQuantity_Lacs":2.22,"volume":222347,"bargraphvalue":"6.60","yearlyPercentageChange":"19.32","totalTradedValue_Crs":70.09,"fiftyTwoWeekLowDateTime":"Oct 26 2023 12:00 AM","monthPrice":3158.95,"companytype":"equity","scripCode2":"PIDILITIND","fiftyTwoWeekLowPrice":"2292.55","nseScripCode":"PIDILITINDEQ","closePrice":"3186.40","seoname":"pidilite-industries-ltd","bestBuyPrice":"3130.20"},{"dateTime":"03:59 PM | 01 Aug 2024","bestSellPrice":"5376.50","symbol":"HEROMOTOCO","companytypeLang":"equity","premarket":"false","companyName":"Hero MotoCorp Ltd.","openPrice":"5487.45","eventCount":0,"bestBuyQty":2191,"companyShortName":"Hero MotoCorp","companyName2":"Hero MotoCorp Ltd.","bargraphFiftyTwoWeek":"82.60","monthlyPercentageChange":"-3.72","companyid":"13636","fiftyTwoWeekHighDateTime":"Jun 18 2024 12:00 AM","fiftyTwoWeekHighPrice":"5894.55","lowPrice":"5325.40","segment":"NSE","highPrice":"5487.45","scripCode":"500182","yearPrice":3172.5,"lastTradedPrice":"5371.85","value":"468.01","netChange":"-116.60","percentChange":"-2.13","monthlyNetChange":"-207.75","yearlyNetChange":"2199.35","bestSellQty":150,"totalTradedQuantity_Lacs":8.68,"volume":868140,"bargraphvalue":"28.66","yearlyPercentageChange":"69.33","totalTradedValue_Crs":468.01,"fiftyTwoWeekLowDateTime":"Aug 25 2023 12:00 AM","monthPrice":5579.6,"companytype":"equity","scripCode2":"HEROMOTOCO","fiftyTwoWeekLowPrice":"2890.00","nseScripCode":"HEROMOTOCOEQ","closePrice":"5488.45","seoname":"hero-motocorp-ltd","bestBuyPrice":"5376.00"}],"index":{"Advances":17,"bestperformer":{"dateTime":"03:57 PM | 01 Aug 2024","bestSellPrice":"6880.95","symbol":"DRREDDY","companytypeLang":"equity","premarket":"false","companyName":"Dr. Reddy's Laboratories Ltd.","openPrice":"6795.50","eventCount":0,"bestBuyQty":1,"companyShortName":"Dr. Reddys","companyName2":"Dr. Reddy's Laboratories Ltd.","bargraphFiftyTwoWeek":"95.57","monthlyPercentageChange":"7.58","companyid":"13841","fiftyTwoWeekHighDateTime":"Jul 26 2024 12:00 AM","fiftyTwoWeekHighPrice":"6966.00","lowPrice":"6786.65","segment":"NSE","highPrice":"6900.50","scripCode":"500124","yearPrice":5583,"lastTradedPrice":"6887.95","value":"318.57","netChange":"137.45","percentChange":"2.04","monthlyNetChange":"485.60","yearlyNetChange":"1304.95","bestSellQty":1,"totalTradedQuantity_Lacs":4.64,"volume":464096,"bargraphvalue":"88.98","yearlyPercentageChange":"23.37","totalTradedValue_Crs":318.57,"fiftyTwoWeekLowDateTime":"Oct 30 2023 12:00 AM","monthPrice":6402.35,"companytype":"equity","scripCode2":"DRREDDY","fiftyTwoWeekLowPrice":"5205.55","nseScripCode":"DRREDDYEQ","closePrice":"6750.50","seoname":"dr-reddys-laboratories-ltd","bestBuyPrice":"6880.80"},"Declines":13,"worstperformer":{"dateTime":"03:59 PM | 01 Aug 2024","bestSellPrice":"5376.50","symbol":"HEROMOTOCO","companytypeLang":"equity","premarket":"false","companyName":"Hero MotoCorp Ltd.","openPrice":"5487.45","eventCount":0,"bestBuyQty":2191,"companyShortName":"Hero MotoCorp","companyName2":"Hero MotoCorp Ltd.","bargraphFiftyTwoWeek":"82.60","monthlyPercentageChange":"-3.72","companyid":"13636","fiftyTwoWeekHighDateTime":"Jun 18 2024 12:00 AM","fiftyTwoWeekHighPrice":"5894.55","lowPrice":"5325.40","segment":"NSE","highPrice":"5487.45","scripCode":"500182","yearPrice":3172.5,"lastTradedPrice":"5371.85","value":"468.01","netChange":"-116.60","percentChange":"-2.13","monthlyNetChange":"-207.75","yearlyNetChange":"2199.35","bestSellQty":150,"totalTradedQuantity_Lacs":8.68,"volume":868140,"bargraphvalue":"28.66","yearlyPercentageChange":"69.33","totalTradedValue_Crs":468.01,"fiftyTwoWeekLowDateTime":"Aug 25 2023 12:00 AM","monthPrice":5579.6,"companytype":"equity","scripCode2":"HEROMOTOCO","fiftyTwoWeekLowPrice":"2890.00","nseScripCode":"HEROMOTOCOEQ","closePrice":"5488.45","seoname":"hero-motocorp-ltd","bestBuyPrice":"5376.00"},"Nochange":0,"AdvancesPercentange":"56.67","indexvalue":{"dateTime":"2024-08-01 16:17:02.0","monthHigh":"20238.00","highprice":"20286.70","indexNameLang":"Nifty 100 Low Volatility 30","monthLow":"19200.4000","futureOptionflag":"false","scripCode2GivenByExchange":"","fiftytwoweeklow":"0.00","advances":16,"nochange":0,"advancesPercentange":53.333336,"nochangePercentange":0,"changevalue":"26.35","declines":14,"openprice":"20254.75","lastvalue":"20238.00","declinesPercentange":46.666668,"fiftytwoweekhigh":"20286.70","percentagechange":"0.13","previousclose":"20211.65","indexname":"Nifty 100 Low Volatility 30","lowprice":"20192.90","scripCode1GivenByExhange":"NIF100LW30","indexid":15501,"exchange":"50","seoname":"nifty-100-low-volatility-30","dateTimeLang":"2024-08-01 16:17:02.0"},"PercentageNochange":0,"DeclinesPercentange":"43.33"}},"pagesummary":{"IndexName":"Nifty 100 Low Volatility 30","totalRecords":30,"lasttradeddate":"04:17 PM | 01 Aug 2024","pageno":1,"stattype":"Live Indices","pagesize":500,"exchange":"NSE","totalpages":1}}
