[
  {
    "name": "IRB",
    "selected": true,
    "price": 71.05,
    "change": 6.44,
    "oichange": 0.0,
    "changePrev": 31.66,
    "oichangePrev": 0.0
  },
  {
    "name": "BORORENEW",
    "selected": true,
    "price": 635.5,
    "change": 1.59,
    "oichange": 0.0,
    "changePrev": 0.4,
    "oichangePrev": 0.0
  },
  {
    "name": "JSWENERGY",
    "selected": true,
    "price": 503.6,
    "change": 4.29,
    "oichange": 0.0,
    "changePrev": -0.97,
    "oichangePrev": 0.0
  },
  {
    "name": "NBCC",
    "selected": true,
    "price": 170.05,
    "change": 0.83,
    "oichange": 0.0,
    "changePrev": 47.04,
    "oichangePrev": 0.0
  },
  {
    "name": "GSFC",
    "selected": true,
    "price": 284.95,
    "change": 0.14,
    "oichange": 0.0,
    "changePrev": -7.34,
    "oichangePrev": 0.0
  },
  {
    "name": "EASEMYTRIP",
    "selected": true,
    "price": 49.7,
    "change": 0.81,
    "oichange": 0.0,
    "changePrev": 4.67,
    "oichangePrev": 0.0
  },
  {
    "name": "NYKAA",
    "selected": true,
    "price": 159.95,
    "change": -1.99,
    "oichange": 0.0,
    "changePrev": 1.3,
    "oichangePrev": 0.0
  },
  {
    "name": "SUPRAJIT",
    "selected": true,
    "price": 388.0,
    "change": -0.39,
    "oichange": 0.0,
    "changePrev": -0.45,
    "oichangePrev": 0.0
  },
  {
    "name": "LATENTVIEW",
    "selected": true,
    "price": 488.6,
    "change": 0.65,
    "oichange": 0.0,
    "changePrev": 7.18,
    "oichangePrev": 0.0
  },
  {
    "name": "ALOKINDS",
    "selected": true,
    "price": 31.25,
    "change": 0.32,
    "oichange": 0.0,
    "changePrev": -3.41,
    "oichangePrev": 0.0
  },
  {
    "name": "PATANJALI",
    "selected": true,
    "price": 1550.0,
    "change": -0.73,
    "oichange": 0.0,
    "changePrev": -1.27,
    "oichangePrev": 0.0
  },
  {
    "name": "SIEMENS",
    "selected": true,
    "price": 4184.95,
    "change": 0.54,
    "oichange": 0.0,
    "changePrev": -1.02,
    "oichangePrev": 0.0
  },
  {
    "name": "TRIDENT",
    "selected": true,
    "price": 47.1,
    "change": 0.21,
    "oichange": 0.0,
    "changePrev": 3.52,
    "oichangePrev": 0.0
  },
  {
    "name": "NAM-INDIA",
    "selected": true,
    "price": 490.05,
    "change": -3.03,
    "oichange": 0.0,
    "changePrev": -2.16,
    "oichangePrev": 0.0
  },
  {
    "name": "DLF",
    "selected": true,
    "price": 803.3,
    "change": 1.5,
    "oichange": 0.0,
    "changePrev": 4.32,
    "oichangePrev": 0.0
  },
  {
    "name": "BAYERCROP",
    "selected": true,
    "price": 5814.15,
    "change": 0.44,
    "oichange": 0.0,
    "changePrev": -1.19,
    "oichangePrev": 0.0
  },
  {
    "name": "PHOENIXLTD",
    "selected": true,
    "price": 2592.35,
    "change": 4.58,
    "oichange": 0.0,
    "changePrev": 7.96,
    "oichangePrev": 0.0
  },
  {
    "name": "MFSL",
    "selected": true,
    "price": 889.1,
    "change": 0.17,
    "oichange": 0.0,
    "changePrev": 1.06,
    "oichangePrev": 0.0
  },
  {
    "name": "NATIONALUM",
    "selected": true,
    "price": 159.2,
    "change": 4.05,
    "oichange": 0.0,
    "changePrev": 8.43,
    "oichangePrev": 0.0
  },
  {
    "name": "GODREJPROP",
    "selected": true,
    "price": 2334.1,
    "change": -1.74,
    "oichange": 0.0,
    "changePrev": 2.09,
    "oichangePrev": 0.0
  },
  {
    "name": "MOTILALOFS",
    "selected": true,
    "price": 1769.7,
    "change": -0.01,
    "oichange": 0.0,
    "changePrev": 2.18,
    "oichangePrev": 0.0
  },
  {
    "name": "ABB",
    "selected": true,
    "price": 4425.8,
    "change": -1.22,
    "oichange": 0.0,
    "changePrev": -5.46,
    "oichangePrev": 0.0
  },
  {
    "name": "KAYNES",
    "selected": true,
    "price": 2854.75,
    "change": -1.81,
    "oichange": 0.0,
    "changePrev": 1.0,
    "oichangePrev": 0.0
  },
  {
    "name": "MINDACORP",
    "selected": true,
    "price": 409.5,
    "change": 1.12,
    "oichange": 0.0,
    "changePrev": -0.8,
    "oichangePrev": 0.0
  },
  {
    "name": "COCHINSHIP",
    "selected": true,
    "price": 913.7,
    "change": 0.94,
    "oichange": 0.0,
    "changePrev": 3.85,
    "oichangePrev": 0.0
  },
  {
    "name": "BLS",
    "selected": true,
    "price": 403.65,
    "change": -1.9,
    "oichange": 0.0,
    "changePrev": 5.66,
    "oichangePrev": 0.0
  },
  {
    "name": "POONAWALLA",
    "selected": true,
    "price": 486.45,
    "change": 4.01,
    "oichange": 0.0,
    "changePrev": -2.09,
    "oichangePrev": 0.0
  },
  {
    "name": "GNFC",
    "selected": true,
    "price": 724.6,
    "change": -1.11,
    "oichange": 0.0,
    "changePrev": 0.02,
    "oichangePrev": 0.0
  },
  {
    "name": "APOLLOTYRE",
    "selected": true,
    "price": 551.5,
    "change": 2.19,
    "oichange": 0.0,
    "changePrev": 4.27,
    "oichangePrev": 0.0
  },
  {
    "name": "CHALET",
    "selected": true,
    "price": 785.0,
    "change": -0.2,
    "oichange": 0.0,
    "changePrev": 3.24,
    "oichangePrev": 0.0
  },
  {
    "name": "OBEROIRLTY",
    "selected": true,
    "price": 1300.35,
    "change": 1.18,
    "oichange": 0.0,
    "changePrev": -1.44,
    "oichangePrev": 0.0
  },
  {
    "name": "BALKRISIND",
    "selected": true,
    "price": 2448.5,
    "change": -0.16,
    "oichange": 0.0,
    "changePrev": -2.95,
    "oichangePrev": 0.0
  },
  {
    "name": "INFIBEAM",
    "selected": true,
    "price": 37.2,
    "change": -3.38,
    "oichange": 0.0,
    "changePrev": 32.3,
    "oichangePrev": 0.0
  },
  {
    "name": "CENTURYTEX",
    "selected": true,
    "price": 1499.95,
    "change": -3.06,
    "oichange": 0.0,
    "changePrev": 15.01,
    "oichangePrev": 0.0
  },
  {
    "name": "SOLARINDS",
    "selected": true,
    "price": 6647.0,
    "change": 3.05,
    "oichange": 0.0,
    "changePrev": -0.89,
    "oichangePrev": 0.0
  },
  {
    "name": "KALYANKJIL",
    "selected": true,
    "price": 339.2,
    "change": -2.5,
    "oichange": 0.0,
    "changePrev": -1.99,
    "oichangePrev": 0.0
  },
  {
    "name": "HEROMOTOCO",
    "selected": true,
    "price": 4760.1,
    "change": 0.91,
    "oichange": 0.0,
    "changePrev": 6.19,
    "oichangePrev": 0.0
  },
  {
    "name": "SUNTECK",
    "selected": true,
    "price": 478.05,
    "change": 2.23,
    "oichange": 0.0,
    "changePrev": 4.46,
    "oichangePrev": 0.0
  },
  {
    "name": "AMBER",
    "selected": true,
    "price": 4428.05,
    "change": -0.33,
    "oichange": 0.0,
    "changePrev": 8.28,
    "oichangePrev": 0.0
  },
  {
    "name": "SUZLON",
    "selected": true,
    "price": 49.4,
    "change": 1.65,
    "oichange": 0.0,
    "changePrev": 14.22,
    "oichangePrev": 0.0
  },
  {
    "name": "ABBOTINDIA",
    "selected": true,
    "price": 27813.0,
    "change": -0.9,
    "oichange": 0.0,
    "changePrev": 11.99,
    "oichangePrev": 0.0
  },
  {
    "name": "RCF",
    "selected": true,
    "price": 172.1,
    "change": -1.21,
    "oichange": 0.0,
    "changePrev": -4.39,
    "oichangePrev": 0.0
  },
  {
    "name": "MANKIND",
    "selected": true,
    "price": 2049.5,
    "change": 0.7,
    "oichange": 0.0,
    "changePrev": 0.24,
    "oichangePrev": 0.0
  },
  {
    "name": "UTIAMC",
    "selected": true,
    "price": 931.85,
    "change": 0.63,
    "oichange": 0.0,
    "changePrev": 7.83,
    "oichangePrev": 0.0
  },
  {
    "name": "GRANULES",
    "selected": true,
    "price": 427.8,
    "change": 1.86,
    "oichange": 0.0,
    "changePrev": 1.4,
    "oichangePrev": 0.0
  },
  {
    "name": "TRENT",
    "selected": true,
    "price": 3047.05,
    "change": -2.53,
    "oichange": 0.0,
    "changePrev": -3.27,
    "oichangePrev": 0.0
  },
  {
    "name": "MAPMYINDIA",
    "selected": true,
    "price": 1830.3,
    "change": -1.16,
    "oichange": 0.0,
    "changePrev": -8.33,
    "oichangePrev": 0.0
  },
  {
    "name": "CESC",
    "selected": true,
    "price": 143.0,
    "change": 3.85,
    "oichange": 0.0,
    "changePrev": 3.3,
    "oichangePrev": 0.0
  },
  {
    "name": "PCBL",
    "selected": true,
    "price": 332.7,
    "change": 3.97,
    "oichange": 0.0,
    "changePrev": -0.71,
    "oichangePrev": 0.0
  },
  {
    "name": "GRINFRA",
    "selected": true,
    "price": 1336.65,
    "change": 5.63,
    "oichange": 0.0,
    "changePrev": 8.8,
    "oichangePrev": 0.0
  },
  {
    "name": "HINDPETRO",
    "selected": true,
    "price": 507.85,
    "change": 3.89,
    "oichange": 0.0,
    "changePrev": 13.53,
    "oichangePrev": 0.0
  },
  {
    "name": "ADANIPORTS",
    "selected": true,
    "price": 1277.95,
    "change": 1.31,
    "oichange": 0.0,
    "changePrev": 10.05,
    "oichangePrev": 0.0
  },
  {
    "name": "VBL",
    "selected": true,
    "price": 1285.7,
    "change": -0.0,
    "oichange": 0.0,
    "changePrev": 2.25,
    "oichangePrev": 0.0
  },
  {
    "name": "MHRIL",
    "selected": true,
    "price": 432.95,
    "change": 3.42,
    "oichange": 0.0,
    "changePrev": 5.28,
    "oichangePrev": 0.0
  },
  {
    "name": "AEGISCHEM",
    "selected": true,
    "price": 395.35,
    "change": 5.61,
    "oichange": 0.0,
    "changePrev": -3.63,
    "oichangePrev": 0.0
  },
  {
    "name": "ECLERX",
    "selected": true,
    "price": 2620.5,
    "change": -2.48,
    "oichange": 0.0,
    "changePrev": 2.96,
    "oichangePrev": 0.0
  },
  {
    "name": "PETRONET",
    "selected": true,
    "price": 272.7,
    "change": 1.21,
    "oichange": 0.0,
    "changePrev": 5.01,
    "oichangePrev": 0.0
  },
  {
    "name": "LEMONTREE",
    "selected": true,
    "price": 142.4,
    "change": 0.25,
    "oichange": 0.0,
    "changePrev": 2.56,
    "oichangePrev": 0.0
  },
  {
    "name": "INDIGO",
    "selected": true,
    "price": 3229.45,
    "change": 3.27,
    "oichange": 0.0,
    "changePrev": 9.22,
    "oichangePrev": 0.0
  },
  {
    "name": "SBILIFE",
    "selected": true,
    "price": 1427.6,
    "change": -0.55,
    "oichange": 0.0,
    "changePrev": 3.95,
    "oichangePrev": 0.0
  },
  {
    "name": "OLECTRA",
    "selected": true,
    "price": 1846.95,
    "change": 3.38,
    "oichange": 0.0,
    "changePrev": 5.23,
    "oichangePrev": 0.0
  },
  {
    "name": "APOLLOHOSP",
    "selected": true,
    "price": 6272.9,
    "change": -0.75,
    "oichange": 0.0,
    "changePrev": 2.46,
    "oichangePrev": 0.0
  },
  {
    "name": "JSL",
    "selected": true,
    "price": 599.35,
    "change": 0.47,
    "oichange": 0.0,
    "changePrev": 10.81,
    "oichangePrev": 0.0
  },
  {
    "name": "INTELLECT",
    "selected": true,
    "price": 921.0,
    "change": 2.91,
    "oichange": 0.0,
    "changePrev": -1.7,
    "oichangePrev": 0.0
  },
  {
    "name": "TIINDIA",
    "selected": true,
    "price": 3643.1,
    "change": -0.02,
    "oichange": 0.0,
    "changePrev": -8.62,
    "oichangePrev": 0.0
  },
  {
    "name": "JINDALSAW",
    "selected": true,
    "price": 497.8,
    "change": 0.51,
    "oichange": 0.0,
    "changePrev": -3.61,
    "oichangePrev": 0.0
  },
  {
    "name": "CREDITACC",
    "selected": true,
    "price": 1597.65,
    "change": -0.65,
    "oichange": 0.0,
    "changePrev": 1.05,
    "oichangePrev": 0.0
  },
  {
    "name": "HDFCAMC",
    "selected": true,
    "price": 3558.35,
    "change": -0.24,
    "oichange": 0.0,
    "changePrev": 4.03,
    "oichangePrev": 0.0
  },
  {
    "name": "RVNL",
    "selected": true,
    "price": 284.3,
    "change": -3.48,
    "oichange": 0.0,
    "changePrev": -2.45,
    "oichangePrev": 0.0
  },
  {
    "name": "ADANIENSOL",
    "selected": true,
    "price": 1039.95,
    "change": -1.15,
    "oichange": 0.0,
    "changePrev": -0.92,
    "oichangePrev": 0.0
  },
  {
    "name": "CEATLTD",
    "selected": true,
    "price": 2660.35,
    "change": 2.04,
    "oichange": 0.0,
    "changePrev": -8.0,
    "oichangePrev": 0.0
  },
  {
    "name": "APLAPOLLO",
    "selected": true,
    "price": 1452.8,
    "change": -1.75,
    "oichange": 0.0,
    "changePrev": -0.75,
    "oichangePrev": 0.0
  },
  {
    "name": "GLS",
    "selected": true,
    "price": 874.15,
    "change": 0.33,
    "oichange": 0.0,
    "changePrev": 4.2,
    "oichangePrev": 0.0
  },
  {
    "name": "ITI",
    "selected": true,
    "price": 355.95,
    "change": 4.11,
    "oichange": 0.0,
    "changePrev": 0.07,
    "oichangePrev": 0.0
  },
  {
    "name": "CONCOR",
    "selected": true,
    "price": 940.1,
    "change": 2.18,
    "oichange": 0.0,
    "changePrev": 11.03,
    "oichangePrev": 0.0
  },
  {
    "name": "AARTIDRUGS",
    "selected": true,
    "price": 512.9,
    "change": 0.7,
    "oichange": 0.0,
    "changePrev": 0.95,
    "oichangePrev": 0.0
  },
  {
    "name": "LTTS",
    "selected": true,
    "price": 5528.6,
    "change": 0.1,
    "oichange": 0.0,
    "changePrev": 2.55,
    "oichangePrev": 0.0
  },
  {
    "name": "BERGEPAINT",
    "selected": true,
    "price": 572.8,
    "change": 0.57,
    "oichange": 0.0,
    "changePrev": 2.68,
    "oichangePrev": 0.0
  },
  {
    "name": "GPIL",
    "selected": true,
    "price": 765.0,
    "change": 1.59,
    "oichange": 0.0,
    "changePrev": -0.87,
    "oichangePrev": 0.0
  },
  {
    "name": "GRINDWELL",
    "selected": true,
    "price": 2269.85,
    "change": -1.01,
    "oichange": 0.0,
    "changePrev": -3.67,
    "oichangePrev": 0.0
  },
  {
    "name": "JUBLPHARMA",
    "selected": true,
    "price": 572.65,
    "change": -3.31,
    "oichange": 0.0,
    "changePrev": 4.13,
    "oichangePrev": 0.0
  },
  {
    "name": "BLUESTARCO",
    "selected": true,
    "price": 1196.85,
    "change": 0.7,
    "oichange": 0.0,
    "changePrev": 12.08,
    "oichangePrev": 0.0
  },
  {
    "name": "QUESS",
    "selected": true,
    "price": 502.4,
    "change": 1.72,
    "oichange": 0.0,
    "changePrev": 2.08,
    "oichangePrev": 0.0
  },
  {
    "name": "ADANIENT",
    "selected": true,
    "price": 3196.05,
    "change": 1.22,
    "oichange": 0.0,
    "changePrev": 9.12,
    "oichangePrev": 0.0
  },
  {
    "name": "GLENMARK",
    "selected": true,
    "price": 888.7,
    "change": 0.34,
    "oichange": 0.0,
    "changePrev": -0.61,
    "oichangePrev": 0.0
  },
  {
    "name": "GODFRYPHLP",
    "selected": true,
    "price": 2472.2,
    "change": -2.83,
    "oichange": 0.0,
    "changePrev": 12.51,
    "oichangePrev": 0.0
  },
  {
    "name": "BAJAJ-AUTO",
    "selected": true,
    "price": 7763.15,
    "change": 0.32,
    "oichange": 0.0,
    "changePrev": 1.85,
    "oichangePrev": 0.0
  },
  {
    "name": "EQUITASBNK",
    "selected": true,
    "price": 104.2,
    "change": -0.29,
    "oichange": 0.0,
    "changePrev": -1.69,
    "oichangePrev": 0.0
  },
  {
    "name": "JINDALSTEL",
    "selected": true,
    "price": 776.2,
    "change": 0.03,
    "oichange": 0.0,
    "changePrev": 8.33,
    "oichangePrev": 0.0
  },
  {
    "name": "INDHOTEL",
    "selected": true,
    "price": 509.55,
    "change": 1.91,
    "oichange": 0.0,
    "changePrev": 5.57,
    "oichangePrev": 0.0
  },
  {
    "name": "TTML",
    "selected": true,
    "price": 94.8,
    "change": 2.65,
    "oichange": 0.0,
    "changePrev": 1.48,
    "oichangePrev": 0.0
  },
  {
    "name": "BHARATFORG",
    "selected": true,
    "price": 1263.75,
    "change": 2.01,
    "oichange": 0.0,
    "changePrev": 3.22,
    "oichangePrev": 0.0
  },
  {
    "name": "IPCALAB",
    "selected": true,
    "price": 1144.15,
    "change": 3.19,
    "oichange": 0.0,
    "changePrev": -0.6,
    "oichangePrev": 0.0
  },
  {
    "name": "BHARTIARTL",
    "selected": true,
    "price": 1120.65,
    "change": -2.62,
    "oichange": 0.0,
    "changePrev": -0.84,
    "oichangePrev": 0.0
  },
  {
    "name": "VTL",
    "selected": true,
    "price": 431.05,
    "change": 2.1,
    "oichange": 0.0,
    "changePrev": 6.33,
    "oichangePrev": 0.0
  },
  {
    "name": "LT",
    "selected": true,
    "price": 3365.0,
    "change": -0.33,
    "oichange": 0.0,
    "changePrev": -6.05,
    "oichangePrev": 0.0
  },
  {
    "name": "MOTHERSON",
    "selected": true,
    "price": 117.35,
    "change": 1.29,
    "oichange": 0.0,
    "changePrev": 0.39,
    "oichangePrev": 0.0
  },
  {
    "name": "BDL",
    "selected": true,
    "price": 1780.05,
    "change": 1.17,
    "oichange": 0.0,
    "changePrev": 5.41,
    "oichangePrev": 0.0
  },
  {
    "name": "MAXHEALTH",
    "selected": true,
    "price": 789.15,
    "change": 2.97,
    "oichange": 0.0,
    "changePrev": 4.63,
    "oichangePrev": 0.0
  },
  {
    "name": "RADICO",
    "selected": true,
    "price": 1740.0,
    "change": 3.3,
    "oichange": 0.0,
    "changePrev": 1.89,
    "oichangePrev": 0.0
  },
  {
    "name": "RAJESHEXPO",
    "selected": true,
    "price": 351.15,
    "change": -0.52,
    "oichange": 0.0,
    "changePrev": 0.47,
    "oichangePrev": 0.0
  },
  {
    "name": "CIPLA",
    "selected": true,
    "price": 1434.25,
    "change": 2.99,
    "oichange": 0.0,
    "changePrev": 1.68,
    "oichangePrev": 0.0
  },
  {
    "name": "EIHOTEL",
    "selected": true,
    "price": 336.0,
    "change": -0.88,
    "oichange": 0.0,
    "changePrev": 9.2,
    "oichangePrev": 0.0
  },
  {
    "name": "GALAXYSURF",
    "selected": true,
    "price": 2645.0,
    "change": 0.85,
    "oichange": 0.0,
    "changePrev": -3.23,
    "oichangePrev": 0.0
  },
  {
    "name": "TATAMTRDVR",
    "selected": true,
    "price": 586.75,
    "change": 9.07,
    "oichange": 0.0,
    "changePrev": -1.38,
    "oichangePrev": 0.0
  },
  {
    "name": "LAURUSLABS",
    "selected": true,
    "price": 389.85,
    "change": -0.7,
    "oichange": 0.0,
    "changePrev": 3.64,
    "oichangePrev": 0.0
  },
  {
    "name": "DIVISLAB",
    "selected": true,
    "price": 3704.1,
    "change": 0.13,
    "oichange": 0.0,
    "changePrev": 3.37,
    "oichangePrev": 0.0
  },
  {
    "name": "SUNPHARMA",
    "selected": true,
    "price": 1455.05,
    "change": 2.71,
    "oichange": 0.0,
    "changePrev": 3.53,
    "oichangePrev": 0.0
  },
  {
    "name": "RITES",
    "selected": true,
    "price": 754.55,
    "change": 7.68,
    "oichange": 0.0,
    "changePrev": 2.34,
    "oichangePrev": 0.0
  },
  {
    "name": "HONAUT",
    "selected": true,
    "price": 38810.0,
    "change": 0.01,
    "oichange": 0.0,
    "changePrev": 0.28,
    "oichangePrev": 0.0
  },
  {
    "name": "IEX",
    "selected": true,
    "price": 148.95,
    "change": 1.99,
    "oichange": 0.0,
    "changePrev": 7.63,
    "oichangePrev": 0.0
  },
  {
    "name": "COALINDIA",
    "selected": true,
    "price": 438.9,
    "change": 4.55,
    "oichange": 0.0,
    "changePrev": 7.81,
    "oichangePrev": 0.0
  },
  {
    "name": "PGHL",
    "selected": true,
    "price": 5158.3,
    "change": -0.56,
    "oichange": 0.0,
    "changePrev": -1.67,
    "oichangePrev": 0.0
  },
  {
    "name": "TATAMOTORS",
    "selected": true,
    "price": 936.8,
    "change": 6.61,
    "oichange": 0.0,
    "changePrev": 8.24,
    "oichangePrev": 0.0
  },
  {
    "name": "BOSCHLTD",
    "selected": true,
    "price": 24226.6,
    "change": 1.13,
    "oichange": 0.0,
    "changePrev": 5.17,
    "oichangePrev": 0.0
  },
  {
    "name": "IRCON",
    "selected": true,
    "price": 228.0,
    "change": -1.94,
    "oichange": 0.0,
    "changePrev": -5.97,
    "oichangePrev": 0.0
  },
  {
    "name": "HUDCO",
    "selected": true,
    "price": 210.85,
    "change": 1.37,
    "oichange": 0.0,
    "changePrev": 27.18,
    "oichangePrev": 0.0
  },
  {
    "name": "CYIENT",
    "selected": true,
    "price": 2143.9,
    "change": 1.62,
    "oichange": 0.0,
    "changePrev": 4.46,
    "oichangePrev": 0.0
  },
  {
    "name": "BSOFT",
    "selected": true,
    "price": 837.85,
    "change": -0.99,
    "oichange": 0.0,
    "changePrev": 3.42,
    "oichangePrev": 0.0
  },
  {
    "name": "MARICO",
    "selected": true,
    "price": 526.5,
    "change": -0.57,
    "oichange": 0.0,
    "changePrev": 0.84,
    "oichangePrev": 0.0
  },
  {
    "name": "SUNDRMFAST",
    "selected": true,
    "price": 1219.1,
    "change": -0.73,
    "oichange": 0.0,
    "changePrev": -3.31,
    "oichangePrev": 0.0
  },
  {
    "name": "BCG",
    "selected": true,
    "price": 20.25,
    "change": 2.02,
    "oichange": 0.0,
    "changePrev": 7.3,
    "oichangePrev": 0.0
  },
  {
    "name": "SYNGENE",
    "selected": true,
    "price": 746.5,
    "change": 0.33,
    "oichange": 0.0,
    "changePrev": 8.57,
    "oichangePrev": 0.0
  },
  {
    "name": "HINDCOPPER",
    "selected": true,
    "price": 302.05,
    "change": 0.32,
    "oichange": 0.0,
    "changePrev": 6.79,
    "oichangePrev": 0.0
  },
  {
    "name": "NCC",
    "selected": true,
    "price": 217.95,
    "change": 1.3,
    "oichange": 0.0,
    "changePrev": 10.62,
    "oichangePrev": 0.0
  },
  {
    "name": "BIRLACORPN",
    "selected": true,
    "price": 1524.9,
    "change": -0.59,
    "oichange": 0.0,
    "changePrev": 9.94,
    "oichangePrev": 0.0
  },
  {
    "name": "BANDHANBNK",
    "selected": true,
    "price": 224.0,
    "change": -2.14,
    "oichange": 0.0,
    "changePrev": 3.6,
    "oichangePrev": 0.0
  },
  {
    "name": "EPL",
    "selected": true,
    "price": 192.25,
    "change": -0.98,
    "oichange": 0.0,
    "changePrev": -2.04,
    "oichangePrev": 0.0
  },
  {
    "name": "CENTURYPLY",
    "selected": true,
    "price": 751.05,
    "change": -4.08,
    "oichange": 0.0,
    "changePrev": -1.22,
    "oichangePrev": 0.0
  },
  {
    "name": "NAUKRI",
    "selected": true,
    "price": 5170.0,
    "change": -0.14,
    "oichange": 0.0,
    "changePrev": 3.91,
    "oichangePrev": 0.0
  },
  {
    "name": "EXIDEIND",
    "selected": true,
    "price": 349.65,
    "change": 1.83,
    "oichange": 0.0,
    "changePrev": 10.62,
    "oichangePrev": 0.0
  },
  {
    "name": "NH",
    "selected": true,
    "price": 1371.55,
    "change": 2.19,
    "oichange": 0.0,
    "changePrev": 6.37,
    "oichangePrev": 0.0
  },
  {
    "name": "BSE",
    "selected": true,
    "price": 2465.0,
    "change": 16.17,
    "oichange": 0.0,
    "changePrev": -6.76,
    "oichangePrev": 0.0
  },
  {
    "name": "TATASTEEL",
    "selected": true,
    "price": 142.1,
    "change": 2.45,
    "oichange": 0.0,
    "changePrev": 3.7,
    "oichangePrev": 0.0
  },
  {
    "name": "JBCHEPHARM",
    "selected": true,
    "price": 1704.95,
    "change": 0.98,
    "oichange": 0.0,
    "changePrev": -0.42,
    "oichangePrev": 0.0
  },
  {
    "name": "CHEMPLASTS",
    "selected": true,
    "price": 470.8,
    "change": -0.93,
    "oichange": 0.0,
    "changePrev": 0.5,
    "oichangePrev": 0.0
  },
  {
    "name": "BPCL",
    "selected": true,
    "price": 583.15,
    "change": 4.44,
    "oichange": 0.0,
    "changePrev": 17.7,
    "oichangePrev": 0.0
  },
  {
    "name": "JKPAPER",
    "selected": true,
    "price": 404.9,
    "change": -2.97,
    "oichange": 0.0,
    "changePrev": -0.81,
    "oichangePrev": 0.0
  },
  {
    "name": "NMDC",
    "selected": true,
    "price": 246.05,
    "change": 4.46,
    "oichange": 0.0,
    "changePrev": 8.47,
    "oichangePrev": 0.0
  },
  {
    "name": "SCHAEFFLER",
    "selected": true,
    "price": 3096.45,
    "change": -1.11,
    "oichange": 0.0,
    "changePrev": 0.68,
    "oichangePrev": 0.0
  },
  {
    "name": "EIDPARRY",
    "selected": true,
    "price": 640.8,
    "change": -0.12,
    "oichange": 0.0,
    "changePrev": 4.02,
    "oichangePrev": 0.0
  },
  {
    "name": "SHYAMMETL",
    "selected": true,
    "price": 698.45,
    "change": -0.98,
    "oichange": 0.0,
    "changePrev": 4.16,
    "oichangePrev": 0.0
  },
  {
    "name": "FIVESTAR",
    "selected": true,
    "price": 778.85,
    "change": 0.43,
    "oichange": 0.0,
    "changePrev": 3.43,
    "oichangePrev": 0.0
  },
  {
    "name": "CIEINDIA",
    "selected": true,
    "price": 497.75,
    "change": 2.26,
    "oichange": 0.0,
    "changePrev": 0.28,
    "oichangePrev": 0.0
  },
  {
    "name": "NTPC",
    "selected": true,
    "price": 340.15,
    "change": 2.3,
    "oichange": 0.0,
    "changePrev": 5.64,
    "oichangePrev": 0.0
  },
  {
    "name": "FSL",
    "selected": true,
    "price": 203.5,
    "change": 2.01,
    "oichange": 0.0,
    "changePrev": 2.41,
    "oichangePrev": 0.0
  },
  {
    "name": "LTIM",
    "selected": true,
    "price": 5485.65,
    "change": -0.0,
    "oichange": 0.0,
    "changePrev": -0.16,
    "oichangePrev": 0.0
  },
  {
    "name": "JMFINANCIL",
    "selected": true,
    "price": 111.3,
    "change": -0.36,
    "oichange": 0.0,
    "changePrev": -1.5,
    "oichangePrev": 0.0
  },
  {
    "name": "CUMMINSIND",
    "selected": true,
    "price": 2337.75,
    "change": 1.21,
    "oichange": 0.0,
    "changePrev": 6.84,
    "oichangePrev": 0.0
  },
  {
    "name": "GUJGASLTD",
    "selected": true,
    "price": 602.45,
    "change": 1.96,
    "oichange": 0.0,
    "changePrev": 6.95,
    "oichangePrev": 0.0
  },
  {
    "name": "DELTACORP",
    "selected": true,
    "price": 137.75,
    "change": 0.11,
    "oichange": 0.0,
    "changePrev": -0.29,
    "oichangePrev": 0.0
  },
  {
    "name": "ZOMATO",
    "selected": true,
    "price": 142.7,
    "change": -0.76,
    "oichange": 0.0,
    "changePrev": 5.62,
    "oichangePrev": 0.0
  },
  {
    "name": "RAINBOW",
    "selected": true,
    "price": 1193.95,
    "change": 1.01,
    "oichange": 0.0,
    "changePrev": -2.88,
    "oichangePrev": 0.0
  },
  {
    "name": "LUPIN",
    "selected": true,
    "price": 1578.2,
    "change": 5.02,
    "oichange": 0.0,
    "changePrev": 3.35,
    "oichangePrev": 0.0
  },
  {
    "name": "GUJALKALI",
    "selected": true,
    "price": 786.75,
    "change": -0.78,
    "oichange": 0.0,
    "changePrev": 3.03,
    "oichangePrev": 0.0
  },
  {
    "name": "PIIND",
    "selected": true,
    "price": 3330.0,
    "change": -1.37,
    "oichange": 0.0,
    "changePrev": 4.14,
    "oichangePrev": 0.0
  },
  {
    "name": "IIFL",
    "selected": true,
    "price": 588.1,
    "change": -1.7,
    "oichange": 0.0,
    "changePrev": -0.58,
    "oichangePrev": 0.0
  },
  {
    "name": "POLICYBZR",
    "selected": true,
    "price": 971.65,
    "change": -0.98,
    "oichange": 0.0,
    "changePrev": 10.48,
    "oichangePrev": 0.0
  },
  {
    "name": "IGL",
    "selected": true,
    "price": 449.9,
    "change": 1.07,
    "oichange": 0.0,
    "changePrev": 9.87,
    "oichangePrev": 0.0
  },
  {
    "name": "JBMA",
    "selected": true,
    "price": 1999.3,
    "change": 2.6,
    "oichange": 0.0,
    "changePrev": 5.37,
    "oichangePrev": 0.0
  },
  {
    "name": "CARBORUNIV",
    "selected": true,
    "price": 1094.55,
    "change": -1.9,
    "oichange": 0.0,
    "changePrev": -2.94,
    "oichangePrev": 0.0
  },
  {
    "name": "LICI",
    "selected": true,
    "price": 1007.95,
    "change": 6.61,
    "oichange": 0.0,
    "changePrev": 4.64,
    "oichangePrev": 0.0
  },
  {
    "name": "AARTIIND",
    "selected": true,
    "price": 642.55,
    "change": -0.33,
    "oichange": 0.0,
    "changePrev": 1.67,
    "oichangePrev": 0.0
  },
  {
    "name": "ISEC",
    "selected": true,
    "price": 817.8,
    "change": 0.07,
    "oichange": 0.0,
    "changePrev": 5.29,
    "oichangePrev": 0.0
  },
  {
    "name": "SPARC",
    "selected": true,
    "price": 369.0,
    "change": 1.43,
    "oichange": 0.0,
    "changePrev": -2.27,
    "oichangePrev": 0.0
  },
  {
    "name": "UNOMINDA",
    "selected": true,
    "price": 687.05,
    "change": -0.15,
    "oichange": 0.0,
    "changePrev": 0.57,
    "oichangePrev": 0.0
  },
  {
    "name": "FEDERALBNK",
    "selected": true,
    "price": 146.45,
    "change": 0.41,
    "oichange": 0.0,
    "changePrev": 2.86,
    "oichangePrev": 0.0
  },
  {
    "name": "KPRMILL",
    "selected": true,
    "price": 796.5,
    "change": 0.86,
    "oichange": 0.0,
    "changePrev": 2.65,
    "oichangePrev": 0.0
  },
  {
    "name": "TATAELXSI",
    "selected": true,
    "price": 7637.7,
    "change": -0.04,
    "oichange": 0.0,
    "changePrev": -0.34,
    "oichangePrev": 0.0
  },
  {
    "name": "VEDL",
    "selected": true,
    "price": 276.55,
    "change": 1.47,
    "oichange": 0.0,
    "changePrev": 3.4,
    "oichangePrev": 0.0
  },
  {
    "name": "SHOPERSTOP",
    "selected": true,
    "price": 751.45,
    "change": 0.19,
    "oichange": 0.0,
    "changePrev": 6.39,
    "oichangePrev": 0.0
  },
  {
    "name": "LODHA",
    "selected": true,
    "price": 1147.1,
    "change": 2.9,
    "oichange": 0.0,
    "changePrev": 5.56,
    "oichangePrev": 0.0
  },
  {
    "name": "POWERINDIA",
    "selected": true,
    "price": 6021.15,
    "change": 4.79,
    "oichange": 0.0,
    "changePrev": -2.44,
    "oichangePrev": 0.0
  },
  {
    "name": "EPIGRAL",
    "selected": true,
    "price": 1012.3,
    "change": -0.93,
    "oichange": 0.0,
    "changePrev": 2.78,
    "oichangePrev": 0.0
  },
  {
    "name": "AWL",
    "selected": true,
    "price": 345.5,
    "change": -1.37,
    "oichange": 0.0,
    "changePrev": -0.2,
    "oichangePrev": 0.0
  },
  {
    "name": "CCL",
    "selected": true,
    "price": 638.45,
    "change": -1.05,
    "oichange": 0.0,
    "changePrev": 0.51,
    "oichangePrev": 0.0
  },
  {
    "name": "ASTRAL",
    "selected": true,
    "price": 1886.65,
    "change": -0.83,
    "oichange": 0.0,
    "changePrev": 5.69,
    "oichangePrev": 0.0
  },
  {
    "name": "JKCEMENT",
    "selected": true,
    "price": 4371.05,
    "change": 0.11,
    "oichange": 0.0,
    "changePrev": 4.77,
    "oichangePrev": 0.0
  },
  {
    "name": "KFINTECH",
    "selected": true,
    "price": 635.0,
    "change": -0.2,
    "oichange": 0.0,
    "changePrev": 17.75,
    "oichangePrev": 0.0
  },
  {
    "name": "SUVENPHAR",
    "selected": true,
    "price": 650.6,
    "change": -0.31,
    "oichange": 0.0,
    "changePrev": -4.25,
    "oichangePrev": 0.0
  },
  {
    "name": "M\u0026M",
    "selected": true,
    "price": 1694.8,
    "change": 2.05,
    "oichange": 0.0,
    "changePrev": 1.54,
    "oichangePrev": 0.0
  },
  {
    "name": "HCLTECH",
    "selected": true,
    "price": 1575.0,
    "change": -0.55,
    "oichange": 0.0,
    "changePrev": 2.16,
    "oichangePrev": 0.0
  },
  {
    "name": "KRBL",
    "selected": true,
    "price": 358.5,
    "change": -0.51,
    "oichange": 0.0,
    "changePrev": -0.21,
    "oichangePrev": 0.0
  },
  {
    "name": "KIMS",
    "selected": true,
    "price": 2082.6,
    "change": -3.03,
    "oichange": 0.0,
    "changePrev": 3.54,
    "oichangePrev": 0.0
  },
  {
    "name": "TORNTPOWER",
    "selected": true,
    "price": 1105.0,
    "change": 3.82,
    "oichange": 0.0,
    "changePrev": 6.34,
    "oichangePrev": 0.0
  },
  {
    "name": "KPITTECH",
    "selected": true,
    "price": 1604.5,
    "change": 1.74,
    "oichange": 0.0,
    "changePrev": 11.42,
    "oichangePrev": 0.0
  },
  {
    "name": "INGERRAND",
    "selected": true,
    "price": 3262.35,
    "change": 0.22,
    "oichange": 0.0,
    "changePrev": 3.91,
    "oichangePrev": 0.0
  },
  {
    "name": "GMMPFAUDLR",
    "selected": true,
    "price": 1518.9,
    "change": 0.44,
    "oichange": 0.0,
    "changePrev": -1.56,
    "oichangePrev": 0.0
  },
  {
    "name": "CANFINHOME",
    "selected": true,
    "price": 820.6,
    "change": -1.0,
    "oichange": 0.0,
    "changePrev": 7.57,
    "oichangePrev": 0.0
  },
  {
    "name": "BBTC",
    "selected": true,
    "price": 1683.0,
    "change": -1.39,
    "oichange": 0.0,
    "changePrev": 2.65,
    "oichangePrev": 0.0
  },
  {
    "name": "MARUTI",
    "selected": true,
    "price": 10516.4,
    "change": -1.3,
    "oichange": 0.0,
    "changePrev": 7.84,
    "oichangePrev": 0.0
  },
  {
    "name": "PNCINFRA",
    "selected": true,
    "price": 437.9,
    "change": -1.66,
    "oichange": 0.0,
    "changePrev": 7.35,
    "oichangePrev": 0.0
  },
  {
    "name": "VIJAYA",
    "selected": true,
    "price": 638.1,
    "change": -1.63,
    "oichange": 0.0,
    "changePrev": 0.11,
    "oichangePrev": 0.0
  },
  {
    "name": "INDIACEM",
    "selected": true,
    "price": 240.15,
    "change": -0.02,
    "oichange": 0.0,
    "changePrev": -4.91,
    "oichangePrev": 0.0
  },
  {
    "name": "SWSOLAR",
    "selected": true,
    "price": 580.6,
    "change": 1.99,
    "oichange": 0.0,
    "changePrev": -1.45,
    "oichangePrev": 0.0
  },
  {
    "name": "TRIVENI",
    "selected": true,
    "price": 351.55,
    "change": 4.04,
    "oichange": 0.0,
    "changePrev": 2.3,
    "oichangePrev": 0.0
  },
  {
    "name": "NATCOPHARM",
    "selected": true,
    "price": 868.45,
    "change": 1.12,
    "oichange": 0.0,
    "changePrev": -1.26,
    "oichangePrev": 0.0
  },
  {
    "name": "TATACONSUM",
    "selected": true,
    "price": 1155.1,
    "change": -0.66,
    "oichange": 0.0,
    "changePrev": 2.29,
    "oichangePrev": 0.0
  },
  {
    "name": "MAZDOCK",
    "selected": true,
    "price": 2134.0,
    "change": -3.25,
    "oichange": 0.0,
    "changePrev": -5.88,
    "oichangePrev": 0.0
  },
  {
    "name": "BANKINDIA",
    "selected": true,
    "price": 141.65,
    "change": -6.53,
    "oichange": 0.0,
    "changePrev": 15.25,
    "oichangePrev": 0.0
  },
  {
    "name": "FACT",
    "selected": true,
    "price": 803.5,
    "change": -2.1,
    "oichange": 0.0,
    "changePrev": -7.45,
    "oichangePrev": 0.0
  },
  {
    "name": "IDBI",
    "selected": true,
    "price": 96.7,
    "change": 10.89,
    "oichange": 0.0,
    "changePrev": 4.43,
    "oichangePrev": 0.0
  },
  {
    "name": "BEL",
    "selected": true,
    "price": 184.25,
    "change": -0.19,
    "oichange": 0.0,
    "changePrev": -2.69,
    "oichangePrev": 0.0
  },
  {
    "name": "RENUKA",
    "selected": true,
    "price": 50.8,
    "change": 2.21,
    "oichange": 0.0,
    "changePrev": 6.31,
    "oichangePrev": 0.0
  },
  {
    "name": "UNIONBANK",
    "selected": true,
    "price": 153.25,
    "change": 2.99,
    "oichange": 0.0,
    "changePrev": 6.02,
    "oichangePrev": 0.0
  },
  {
    "name": "DIXON",
    "selected": true,
    "price": 6290.25,
    "change": 0.84,
    "oichange": 0.0,
    "changePrev": 6.09,
    "oichangePrev": 0.0
  },
  {
    "name": "TECHM",
    "selected": true,
    "price": 1346.35,
    "change": 0.62,
    "oichange": 0.0,
    "changePrev": 1.21,
    "oichangePrev": 0.0
  },
  {
    "name": "TORNTPHARM",
    "selected": true,
    "price": 2672.2,
    "change": 5.8,
    "oichange": 0.0,
    "changePrev": 2.11,
    "oichangePrev": 0.0
  },
  {
    "name": "RAYMOND",
    "selected": true,
    "price": 1746.9,
    "change": -1.84,
    "oichange": 0.0,
    "changePrev": 1.56,
    "oichangePrev": 0.0
  },
  {
    "name": "TATACOMM",
    "selected": true,
    "price": 1700.5,
    "change": 0.11,
    "oichange": 0.0,
    "changePrev": -1.04,
    "oichangePrev": 0.0
  },
  {
    "name": "INDIGOPNTS",
    "selected": true,
    "price": 1416.3,
    "change": -0.18,
    "oichange": 0.0,
    "changePrev": -2.14,
    "oichangePrev": 0.0
  },
  {
    "name": "FINPIPE",
    "selected": true,
    "price": 219.0,
    "change": 0.6,
    "oichange": 0.0,
    "changePrev": -3.27,
    "oichangePrev": 0.0
  },
  {
    "name": "HAL",
    "selected": true,
    "price": 2972.0,
    "change": 0.04,
    "oichange": 0.0,
    "changePrev": 2.3,
    "oichangePrev": 0.0
  },
  {
    "name": "JUSTDIAL",
    "selected": true,
    "price": 811.05,
    "change": 0.28,
    "oichange": 0.0,
    "changePrev": -3.91,
    "oichangePrev": 0.0
  },
  {
    "name": "LUXIND",
    "selected": true,
    "price": 1214.1,
    "change": 0.11,
    "oichange": 0.0,
    "changePrev": -3.35,
    "oichangePrev": 0.0
  },
  {
    "name": "AUROPHARMA",
    "selected": true,
    "price": 1054.75,
    "change": -1.12,
    "oichange": 0.0,
    "changePrev": -7.31,
    "oichangePrev": 0.0
  },
  {
    "name": "WELSPUNLIV",
    "selected": true,
    "price": 157.25,
    "change": 0.64,
    "oichange": 0.0,
    "changePrev": -4.23,
    "oichangePrev": 0.0
  },
  {
    "name": "HAPPSTMNDS",
    "selected": true,
    "price": 862.35,
    "change": -1.32,
    "oichange": 0.0,
    "changePrev": 0.85,
    "oichangePrev": 0.0
  },
  {
    "name": "DEEPAKNTR",
    "selected": true,
    "price": 2234.0,
    "change": -0.72,
    "oichange": 0.0,
    "changePrev": 0.61,
    "oichangePrev": 0.0
  },
  {
    "name": "GLAND",
    "selected": true,
    "price": 2025.1,
    "change": 1.33,
    "oichange": 0.0,
    "changePrev": 5.24,
    "oichangePrev": 0.0
  },
  {
    "name": "TANLA",
    "selected": true,
    "price": 1001.7,
    "change": -0.6,
    "oichange": 0.0,
    "changePrev": -2.87,
    "oichangePrev": 0.0
  },
  {
    "name": "BIOCON",
    "selected": true,
    "price": 286.0,
    "change": 4.11,
    "oichange": 0.0,
    "changePrev": 6.18,
    "oichangePrev": 0.0
  },
  {
    "name": "GRAPHITE",
    "selected": true,
    "price": 594.4,
    "change": 7.59,
    "oichange": 0.0,
    "changePrev": 4.19,
    "oichangePrev": 0.0
  },
  {
    "name": "HAVELLS",
    "selected": true,
    "price": 1352.15,
    "change": 0.81,
    "oichange": 0.0,
    "changePrev": 3.95,
    "oichangePrev": 0.0
  },
  {
    "name": "SFL",
    "selected": true,
    "price": 1140.85,
    "change": 0.92,
    "oichange": 0.0,
    "changePrev": -0.65,
    "oichangePrev": 0.0
  },
  {
    "name": "ENGINERSIN",
    "selected": true,
    "price": 248.55,
    "change": -4.9,
    "oichange": 0.0,
    "changePrev": 12.38,
    "oichangePrev": 0.0
  },
  {
    "name": "PPLPHARMA",
    "selected": true,
    "price": 139.25,
    "change": 1.16,
    "oichange": 0.0,
    "changePrev": -3.61,
    "oichangePrev": 0.0
  },
  {
    "name": "INFY",
    "selected": true,
    "price": 1699.2,
    "change": 0.35,
    "oichange": 0.0,
    "changePrev": 1.45,
    "oichangePrev": 0.0
  },
  {
    "name": "UJJIVANSFB",
    "selected": true,
    "price": 56.95,
    "change": 2.24,
    "oichange": 0.0,
    "changePrev": 1.92,
    "oichangePrev": 0.0
  },
  {
    "name": "ALKYLAMINE",
    "selected": true,
    "price": 2250.0,
    "change": -2.54,
    "oichange": 0.0,
    "changePrev": 2.42,
    "oichangePrev": 0.0
  },
  {
    "name": "DEVYANI",
    "selected": true,
    "price": 165.0,
    "change": -4.62,
    "oichange": 0.0,
    "changePrev": -2.89,
    "oichangePrev": 0.0
  },
  {
    "name": "YESBANK",
    "selected": true,
    "price": 23.15,
    "change": -2.32,
    "oichange": 0.0,
    "changePrev": -4.63,
    "oichangePrev": 0.0
  },
  {
    "name": "TTKPRESTIG",
    "selected": true,
    "price": 784.8,
    "change": 0.92,
    "oichange": 0.0,
    "changePrev": -0.12,
    "oichangePrev": 0.0
  },
  {
    "name": "SUNTV",
    "selected": true,
    "price": 654.65,
    "change": 0.63,
    "oichange": 0.0,
    "changePrev": 0.12,
    "oichangePrev": 0.0
  },
  {
    "name": "IRFC",
    "selected": true,
    "price": 162.2,
    "change": -4.0,
    "oichange": 0.0,
    "changePrev": -2.82,
    "oichangePrev": 0.0
  },
  {
    "name": "PIDILITIND",
    "selected": true,
    "price": 2538.0,
    "change": 0.9,
    "oichange": 0.0,
    "changePrev": -2.89,
    "oichangePrev": 0.0
  },
  {
    "name": "TATAPOWER",
    "selected": true,
    "price": 400.1,
    "change": 2.64,
    "oichange": 0.0,
    "changePrev": 6.77,
    "oichangePrev": 0.0
  },
  {
    "name": "CRISIL",
    "selected": true,
    "price": 4134.05,
    "change": -1.0,
    "oichange": 0.0,
    "changePrev": 9.39,
    "oichangePrev": 0.0
  },
  {
    "name": "WHIRLPOOL",
    "selected": true,
    "price": 1367.5,
    "change": 1.54,
    "oichange": 0.0,
    "changePrev": 2.26,
    "oichangePrev": 0.0
  },
  {
    "name": "ZYDUSLIFE",
    "selected": true,
    "price": 759.1,
    "change": -0.27,
    "oichange": 0.0,
    "changePrev": 3.35,
    "oichangePrev": 0.0
  },
  {
    "name": "MSUMI",
    "selected": true,
    "price": 72.6,
    "change": 4.61,
    "oichange": 0.0,
    "changePrev": 13.86,
    "oichangePrev": 0.0
  },
  {
    "name": "CGPOWER",
    "selected": true,
    "price": 439.35,
    "change": -1.93,
    "oichange": 0.0,
    "changePrev": -3.26,
    "oichangePrev": 0.0
  },
  {
    "name": "VINATIORGA",
    "selected": true,
    "price": 1691.2,
    "change": -1.42,
    "oichange": 0.0,
    "changePrev": 1.85,
    "oichangePrev": 0.0
  },
  {
    "name": "3MINDIA",
    "selected": true,
    "price": 32500.0,
    "change": -1.12,
    "oichange": 0.0,
    "changePrev": -3.46,
    "oichangePrev": 0.0
  },
  {
    "name": "CROMPTON",
    "selected": true,
    "price": 306.15,
    "change": 0.54,
    "oichange": 0.0,
    "changePrev": -0.2,
    "oichangePrev": 0.0
  },
  {
    "name": "360ONE",
    "selected": true,
    "price": 605.8,
    "change": 0.14,
    "oichange": 0.0,
    "changePrev": -4.01,
    "oichangePrev": 0.0
  },
  {
    "name": "BHEL",
    "selected": true,
    "price": 241.8,
    "change": 3.42,
    "oichange": 0.0,
    "changePrev": 6.32,
    "oichangePrev": 0.0
  },
  {
    "name": "CHAMBLFERT",
    "selected": true,
    "price": 354.7,
    "change": -1.34,
    "oichange": 0.0,
    "changePrev": -2.47,
    "oichangePrev": 0.0
  },
  {
    "name": "GSPL",
    "selected": true,
    "price": 364.0,
    "change": 3.88,
    "oichange": 0.0,
    "changePrev": -2.98,
    "oichangePrev": 0.0
  },
  {
    "name": "FINCABLES",
    "selected": true,
    "price": 1082.0,
    "change": 1.62,
    "oichange": 0.0,
    "changePrev": -3.8,
    "oichangePrev": 0.0
  },
  {
    "name": "LICHSGFIN",
    "selected": true,
    "price": 644.55,
    "change": 1.62,
    "oichange": 0.0,
    "changePrev": 9.5,
    "oichangePrev": 0.0
  },
  {
    "name": "KARURVYSYA",
    "selected": true,
    "price": 192.85,
    "change": -0.34,
    "oichange": 0.0,
    "changePrev": 7.35,
    "oichangePrev": 0.0
  },
  {
    "name": "VOLTAS",
    "selected": true,
    "price": 1031.4,
    "change": -2.55,
    "oichange": 0.0,
    "changePrev": 5.29,
    "oichangePrev": 0.0
  },
  {
    "name": "FINEORG",
    "selected": true,
    "price": 4522.9,
    "change": -3.1,
    "oichange": 0.0,
    "changePrev": -0.08,
    "oichangePrev": 0.0
  },
  {
    "name": "KANSAINER",
    "selected": true,
    "price": 340.75,
    "change": 0.07,
    "oichange": 0.0,
    "changePrev": 2.33,
    "oichangePrev": 0.0
  },
  {
    "name": "ADANIGREEN",
    "selected": true,
    "price": 1657.5,
    "change": -1.0,
    "oichange": 0.0,
    "changePrev": 0.57,
    "oichangePrev": 0.0
  },
  {
    "name": "JYOTHYLAB",
    "selected": true,
    "price": 498.9,
    "change": -2.12,
    "oichange": 0.0,
    "changePrev": -6.75,
    "oichangePrev": 0.0
  },
  {
    "name": "ZFCVINDIA",
    "selected": true,
    "price": 14858.95,
    "change": -0.3,
    "oichange": 0.0,
    "changePrev": -10.84,
    "oichangePrev": 0.0
  },
  {
    "name": "AIAENG",
    "selected": true,
    "price": 4412.95,
    "change": -1.08,
    "oichange": 0.0,
    "changePrev": 14.54,
    "oichangePrev": 0.0
  },
  {
    "name": "MASTEK",
    "selected": true,
    "price": 2899.4,
    "change": -1.65,
    "oichange": 0.0,
    "changePrev": 7.26,
    "oichangePrev": 0.0
  },
  {
    "name": "NIACL",
    "selected": true,
    "price": 266.3,
    "change": 10.0,
    "oichange": 0.0,
    "changePrev": 4.62,
    "oichangePrev": 0.0
  },
  {
    "name": "ASTERDM",
    "selected": true,
    "price": 428.3,
    "change": -0.02,
    "oichange": 0.0,
    "changePrev": -0.51,
    "oichangePrev": 0.0
  },
  {
    "name": "IRCTC",
    "selected": true,
    "price": 953.55,
    "change": -1.44,
    "oichange": 0.0,
    "changePrev": -0.29,
    "oichangePrev": 0.0
  },
  {
    "name": "COFORGE",
    "selected": true,
    "price": 6385.1,
    "change": -0.63,
    "oichange": 0.0,
    "changePrev": 3.55,
    "oichangePrev": 0.0
  },
  {
    "name": "AETHER",
    "selected": true,
    "price": 839.15,
    "change": -0.81,
    "oichange": 0.0,
    "changePrev": -0.15,
    "oichangePrev": 0.0
  },
  {
    "name": "TCS",
    "selected": true,
    "price": 4008.55,
    "change": 1.07,
    "oichange": 0.0,
    "changePrev": 4.09,
    "oichangePrev": 0.0
  },
  {
    "name": "ROUTE",
    "selected": true,
    "price": 1585.15,
    "change": 0.18,
    "oichange": 0.0,
    "changePrev": 0.43,
    "oichangePrev": 0.0
  },
  {
    "name": "SONATSOFTW",
    "selected": true,
    "price": 808.6,
    "change": 5.23,
    "oichange": 0.0,
    "changePrev": 2.66,
    "oichangePrev": 0.0
  },
  {
    "name": "GICRE",
    "selected": true,
    "price": 428.6,
    "change": 13.63,
    "oichange": 0.0,
    "changePrev": 6.96,
    "oichangePrev": 0.0
  },
  {
    "name": "PRESTIGE",
    "selected": true,
    "price": 1205.6,
    "change": -0.51,
    "oichange": 0.0,
    "changePrev": 0.59,
    "oichangePrev": 0.0
  },
  {
    "name": "UCOBANK",
    "selected": true,
    "price": 59.1,
    "change": 16.91,
    "oichange": 0.0,
    "changePrev": 22.69,
    "oichangePrev": 0.0
  },
  {
    "name": "AFFLE",
    "selected": true,
    "price": 1204.65,
    "change": -2.11,
    "oichange": 0.0,
    "changePrev": 0.9,
    "oichangePrev": 0.0
  },
  {
    "name": "AVANTIFEED",
    "selected": true,
    "price": 543.7,
    "change": -1.43,
    "oichange": 0.0,
    "changePrev": 8.76,
    "oichangePrev": 0.0
  },
  {
    "name": "SAIL",
    "selected": true,
    "price": 135.35,
    "change": 5.49,
    "oichange": 0.0,
    "changePrev": 7.72,
    "oichangePrev": 0.0
  },
  {
    "name": "BRIGADE",
    "selected": true,
    "price": 1033.05,
    "change": 0.09,
    "oichange": 0.0,
    "changePrev": 5.86,
    "oichangePrev": 0.0
  },
  {
    "name": "JUBLINGREA",
    "selected": true,
    "price": 427.95,
    "change": 0.28,
    "oichange": 0.0,
    "changePrev": -8.16,
    "oichangePrev": 0.0
  },
  {
    "name": "GAIL",
    "selected": true,
    "price": 185.5,
    "change": 4.27,
    "oichange": 0.0,
    "changePrev": 7.56,
    "oichangePrev": 0.0
  },
  {
    "name": "PERSISTENT",
    "selected": true,
    "price": 8513.0,
    "change": 0.12,
    "oichange": 0.0,
    "changePrev": 1.48,
    "oichangePrev": 0.0
  },
  {
    "name": "SHARDACROP",
    "selected": true,
    "price": 384.9,
    "change": 0.35,
    "oichange": 0.0,
    "changePrev": -3.75,
    "oichangePrev": 0.0
  },
  {
    "name": "BALRAMCHIN",
    "selected": true,
    "price": 396.0,
    "change": 0.74,
    "oichange": 0.0,
    "changePrev": 1.38,
    "oichangePrev": 0.0
  },
  {
    "name": "CONCORDBIO",
    "selected": true,
    "price": 1457.4,
    "change": -0.46,
    "oichange": 0.0,
    "changePrev": 5.63,
    "oichangePrev": 0.0
  },
  {
    "name": "CAMS",
    "selected": true,
    "price": 2910.75,
    "change": 0.88,
    "oichange": 0.0,
    "changePrev": 5.03,
    "oichangePrev": 0.0
  },
  {
    "name": "SONACOMS",
    "selected": true,
    "price": 642.0,
    "change": 1.85,
    "oichange": 0.0,
    "changePrev": 7.68,
    "oichangePrev": 0.0
  },
  {
    "name": "MRPL",
    "selected": true,
    "price": 198.5,
    "change": 3.6,
    "oichange": 0.0,
    "changePrev": 9.86,
    "oichangePrev": 0.0
  },
  {
    "name": "KOTAKBANK",
    "selected": true,
    "price": 1806.75,
    "change": -0.89,
    "oichange": 0.0,
    "changePrev": 3.08,
    "oichangePrev": 0.0
  },
  {
    "name": "CHOLAHLDNG",
    "selected": true,
    "price": 1151.5,
    "change": 0.73,
    "oichange": 0.0,
    "changePrev": 3.78,
    "oichangePrev": 0.0
  },
  {
    "name": "TATACHEM",
    "selected": true,
    "price": 986.65,
    "change": -1.07,
    "oichange": 0.0,
    "changePrev": -0.83,
    "oichangePrev": 0.0
  },
  {
    "name": "IOB",
    "selected": true,
    "price": 64.35,
    "change": 14.6,
    "oichange": 0.0,
    "changePrev": 22.73,
    "oichangePrev": 0.0
  },
  {
    "name": "PNB",
    "selected": true,
    "price": 124.7,
    "change": -0.56,
    "oichange": 0.0,
    "changePrev": 20.0,
    "oichangePrev": 0.0
  },
  {
    "name": "MAHABANK",
    "selected": true,
    "price": 62.35,
    "change": 8.62,
    "oichange": 0.0,
    "changePrev": 7.49,
    "oichangePrev": 0.0
  },
  {
    "name": "MRF",
    "selected": true,
    "price": 141999.35,
    "change": 0.75,
    "oichange": 0.0,
    "changePrev": 2.98,
    "oichangePrev": 0.0
  },
  {
    "name": "MCDOWELL-N",
    "selected": true,
    "price": 1074.4,
    "change": -1.07,
    "oichange": 0.0,
    "changePrev": -0.91,
    "oichangePrev": 0.0
  },
  {
    "name": "DMART",
    "selected": true,
    "price": 3737.2,
    "change": -1.24,
    "oichange": 0.0,
    "changePrev": 1.34,
    "oichangePrev": 0.0
  },
  {
    "name": "NSLNISP",
    "selected": true,
    "price": 71.3,
    "change": 0.56,
    "oichange": 0.0,
    "changePrev": 20.78,
    "oichangePrev": 0.0
  },
  {
    "name": "AAVAS",
    "selected": true,
    "price": 1446.1,
    "change": -2.56,
    "oichange": 0.0,
    "changePrev": -1.6,
    "oichangePrev": 0.0
  },
  {
    "name": "WIPRO",
    "selected": true,
    "price": 484.2,
    "change": 0.22,
    "oichange": 0.0,
    "changePrev": 2.8,
    "oichangePrev": 0.0
  },
  {
    "name": "SAFARI",
    "selected": true,
    "price": 2011.95,
    "change": -0.73,
    "oichange": 0.0,
    "changePrev": 6.11,
    "oichangePrev": 0.0
  },
  {
    "name": "SHREECEM",
    "selected": true,
    "price": 27626.4,
    "change": -2.91,
    "oichange": 0.0,
    "changePrev": 1.81,
    "oichangePrev": 0.0
  },
  {
    "name": "ATGL",
    "selected": true,
    "price": 999.1,
    "change": -0.02,
    "oichange": 0.0,
    "changePrev": -0.37,
    "oichangePrev": 0.0
  },
  {
    "name": "JSWSTEEL",
    "selected": true,
    "price": 822.5,
    "change": -0.13,
    "oichange": 0.0,
    "changePrev": 0.96,
    "oichangePrev": 0.0
  },
  {
    "name": "CANBK",
    "selected": true,
    "price": 521.15,
    "change": 1.32,
    "oichange": 0.0,
    "changePrev": 10.54,
    "oichangePrev": 0.0
  },
  {
    "name": "FDC",
    "selected": true,
    "price": 429.0,
    "change": 1.37,
    "oichange": 0.0,
    "changePrev": 1.43,
    "oichangePrev": 0.0
  },
  {
    "name": "KAJARIACER",
    "selected": true,
    "price": 1315.0,
    "change": -2.22,
    "oichange": 0.0,
    "changePrev": 0.4,
    "oichangePrev": 0.0
  },
  {
    "name": "POWERGRID",
    "selected": true,
    "price": 288.35,
    "change": 4.06,
    "oichange": 0.0,
    "changePrev": 12.87,
    "oichangePrev": 0.0
  },
  {
    "name": "CHOLAFIN",
    "selected": true,
    "price": 1156.15,
    "change": -0.4,
    "oichange": 0.0,
    "changePrev": -6.74,
    "oichangePrev": 0.0
  },
  {
    "name": "CDSL",
    "selected": true,
    "price": 1873.8,
    "change": 5.85,
    "oichange": 0.0,
    "changePrev": -2.78,
    "oichangePrev": 0.0
  },
  {
    "name": "HOMEFIRST",
    "selected": true,
    "price": 965.8,
    "change": -1.62,
    "oichange": 0.0,
    "changePrev": 1.79,
    "oichangePrev": 0.0
  },
  {
    "name": "OFSS",
    "selected": true,
    "price": 6743.9,
    "change": 2.74,
    "oichange": 0.0,
    "changePrev": -2.13,
    "oichangePrev": 0.0
  },
  {
    "name": "PNBHOUSING",
    "selected": true,
    "price": 814.0,
    "change": 1.64,
    "oichange": 0.0,
    "changePrev": -2.44,
    "oichangePrev": 0.0
  },
  {
    "name": "HLEGLAS",
    "selected": true,
    "price": 522.45,
    "change": -2.13,
    "oichange": 0.0,
    "changePrev": -1.39,
    "oichangePrev": 0.0
  },
  {
    "name": "HINDUNILVR",
    "selected": true,
    "price": 2442.2,
    "change": -0.42,
    "oichange": 0.0,
    "changePrev": 1.0,
    "oichangePrev": 0.0
  },
  {
    "name": "NAZARA",
    "selected": true,
    "price": 853.15,
    "change": -1.0,
    "oichange": 0.0,
    "changePrev": -5.35,
    "oichangePrev": 0.0
  },
  {
    "name": "SYRMA",
    "selected": true,
    "price": 569.95,
    "change": -1.97,
    "oichange": 0.0,
    "changePrev": -3.18,
    "oichangePrev": 0.0
  },
  {
    "name": "METROPOLIS",
    "selected": true,
    "price": 1657.1,
    "change": 1.21,
    "oichange": 0.0,
    "changePrev": 5.04,
    "oichangePrev": 0.0
  },
  {
    "name": "STARHEALTH",
    "selected": true,
    "price": 574.05,
    "change": 0.04,
    "oichange": 0.0,
    "changePrev": 3.25,
    "oichangePrev": 0.0
  },
  {
    "name": "TEAMLEASE",
    "selected": true,
    "price": 2956.85,
    "change": -0.49,
    "oichange": 0.0,
    "changePrev": -1.98,
    "oichangePrev": 0.0
  },
  {
    "name": "BAJFINANCE",
    "selected": true,
    "price": 6764.8,
    "change": -1.22,
    "oichange": 0.0,
    "changePrev": -3.35,
    "oichangePrev": 0.0
  },
  {
    "name": "ICICIGI",
    "selected": true,
    "price": 1514.45,
    "change": 1.03,
    "oichange": 0.0,
    "changePrev": 1.14,
    "oichangePrev": 0.0
  },
  {
    "name": "PRSMJOHNSN",
    "selected": true,
    "price": 170.15,
    "change": -0.03,
    "oichange": 0.0,
    "changePrev": 1.22,
    "oichangePrev": 0.0
  },
  {
    "name": "OIL",
    "selected": true,
    "price": 454.15,
    "change": 1.62,
    "oichange": 0.0,
    "changePrev": 10.87,
    "oichangePrev": 0.0
  },
  {
    "name": "ADANIPOWER",
    "selected": true,
    "price": 548.5,
    "change": -1.95,
    "oichange": 0.0,
    "changePrev": 2.96,
    "oichangePrev": 0.0
  },
  {
    "name": "ABCAPITAL",
    "selected": true,
    "price": 178.85,
    "change": -0.83,
    "oichange": 0.0,
    "changePrev": 8.81,
    "oichangePrev": 0.0
  },
  {
    "name": "GPPL",
    "selected": true,
    "price": 184.65,
    "change": 1.26,
    "oichange": 0.0,
    "changePrev": 11.46,
    "oichangePrev": 0.0
  },
  {
    "name": "LINDEINDIA",
    "selected": true,
    "price": 5663.45,
    "change": 2.04,
    "oichange": 0.0,
    "changePrev": -2.87,
    "oichangePrev": 0.0
  },
  {
    "name": "CERA",
    "selected": true,
    "price": 8244.2,
    "change": 0.06,
    "oichange": 0.0,
    "changePrev": 0.64,
    "oichangePrev": 0.0
  },
  {
    "name": "ICICIBANK",
    "selected": true,
    "price": 1023.2,
    "change": -0.08,
    "oichange": 0.0,
    "changePrev": 1.39,
    "oichangePrev": 0.0
  },
  {
    "name": "CASTROLIND",
    "selected": true,
    "price": 201.2,
    "change": 1.41,
    "oichange": 0.0,
    "changePrev": 13.31,
    "oichangePrev": 0.0
  },
  {
    "name": "PEL",
    "selected": true,
    "price": 910.85,
    "change": -1.19,
    "oichange": 0.0,
    "changePrev": 5.48,
    "oichangePrev": 0.0
  },
  {
    "name": "BANKBARODA",
    "selected": true,
    "price": 259.85,
    "change": 1.8,
    "oichange": 0.0,
    "changePrev": 12.42,
    "oichangePrev": 0.0
  },
  {
    "name": "PGHH",
    "selected": true,
    "price": 16919.8,
    "change": 0.14,
    "oichange": 0.0,
    "changePrev": -1.09,
    "oichangePrev": 0.0
  },
  {
    "name": "NHPC",
    "selected": true,
    "price": 111.95,
    "change": 11.23,
    "oichange": 0.0,
    "changePrev": 20.83,
    "oichangePrev": 0.0
  },
  {
    "name": "RAMCOCEM",
    "selected": true,
    "price": 988.25,
    "change": -0.48,
    "oichange": 0.0,
    "changePrev": 2.5,
    "oichangePrev": 0.0
  },
  {
    "name": "ELGIEQUIP",
    "selected": true,
    "price": 598.55,
    "change": -1.33,
    "oichange": 0.0,
    "changePrev": 4.49,
    "oichangePrev": 0.0
  },
  {
    "name": "ORIENTELEC",
    "selected": true,
    "price": 223.8,
    "change": 1.61,
    "oichange": 0.0,
    "changePrev": 4.91,
    "oichangePrev": 0.0
  },
  {
    "name": "RELAXO",
    "selected": true,
    "price": 842.4,
    "change": 0.42,
    "oichange": 0.0,
    "changePrev": -1.47,
    "oichangePrev": 0.0
  },
  {
    "name": "INDUSINDBK",
    "selected": true,
    "price": 1539.6,
    "change": 0.38,
    "oichange": 0.0,
    "changePrev": 1.44,
    "oichangePrev": 0.0
  },
  {
    "name": "STLTECH",
    "selected": true,
    "price": 140.3,
    "change": -0.04,
    "oichange": 0.0,
    "changePrev": 2.52,
    "oichangePrev": 0.0
  },
  {
    "name": "TATAINVEST",
    "selected": true,
    "price": 5712.9,
    "change": 0.57,
    "oichange": 0.0,
    "changePrev": 25.03,
    "oichangePrev": 0.0
  },
  {
    "name": "SYMPHONY",
    "selected": true,
    "price": 937.05,
    "change": -0.09,
    "oichange": 0.0,
    "changePrev": 0.9,
    "oichangePrev": 0.0
  },
  {
    "name": "SANOFI",
    "selected": true,
    "price": 8910.95,
    "change": -0.12,
    "oichange": 0.0,
    "changePrev": 6.98,
    "oichangePrev": 0.0
  },
  {
    "name": "ITC",
    "selected": true,
    "price": 442.35,
    "change": 0.51,
    "oichange": 0.0,
    "changePrev": -3.41,
    "oichangePrev": 0.0
  },
  {
    "name": "TITAN",
    "selected": true,
    "price": 3588.9,
    "change": -0.65,
    "oichange": 0.0,
    "changePrev": -4.19,
    "oichangePrev": 0.0
  },
  {
    "name": "ULTRACEMCO",
    "selected": true,
    "price": 10006.45,
    "change": -0.91,
    "oichange": 0.0,
    "changePrev": 1.3,
    "oichangePrev": 0.0
  },
  {
    "name": "HINDALCO",
    "selected": true,
    "price": 585.6,
    "change": 0.36,
    "oichange": 0.0,
    "changePrev": 2.87,
    "oichangePrev": 0.0
  },
  {
    "name": "DRREDDY",
    "selected": true,
    "price": 6118.2,
    "change": 1.3,
    "oichange": 0.0,
    "changePrev": 3.14,
    "oichangePrev": 0.0
  },
  {
    "name": "SJVN",
    "selected": true,
    "price": 167.5,
    "change": 17.75,
    "oichange": 0.0,
    "changePrev": 22.16,
    "oichangePrev": 0.0
  },
  {
    "name": "APLLTD",
    "selected": true,
    "price": 984.35,
    "change": 2.81,
    "oichange": 0.0,
    "changePrev": 1.67,
    "oichangePrev": 0.0
  },
  {
    "name": "HINDZINC",
    "selected": true,
    "price": 315.6,
    "change": -0.82,
    "oichange": 0.0,
    "changePrev": 1.6,
    "oichangePrev": 0.0
  },
  {
    "name": "SBIN",
    "selected": true,
    "price": 647.55,
    "change": -0.32,
    "oichange": 0.0,
    "changePrev": 6.02,
    "oichangePrev": 0.0
  },
  {
    "name": "RELIANCE",
    "selected": true,
    "price": 2919.2,
    "change": 0.13,
    "oichange": 0.0,
    "changePrev": 7.73,
    "oichangePrev": 0.0
  },
  {
    "name": "EICHERMOT",
    "selected": true,
    "price": 3898.25,
    "change": 1.9,
    "oichange": 0.0,
    "changePrev": 5.78,
    "oichangePrev": 0.0
  },
  {
    "name": "PRINCEPIPE",
    "selected": true,
    "price": 720.0,
    "change": 2.69,
    "oichange": 0.0,
    "changePrev": 1.73,
    "oichangePrev": 0.0
  },
  {
    "name": "MGL",
    "selected": true,
    "price": 1488.8,
    "change": 0.8,
    "oichange": 0.0,
    "changePrev": 7.48,
    "oichangePrev": 0.0
  },
  {
    "name": "ERIS",
    "selected": true,
    "price": 887.05,
    "change": -0.56,
    "oichange": 0.0,
    "changePrev": 0.3,
    "oichangePrev": 0.0
  },
  {
    "name": "BEML",
    "selected": true,
    "price": 3729.95,
    "change": -2.51,
    "oichange": 0.0,
    "changePrev": 19.53,
    "oichangePrev": 0.0
  },
  {
    "name": "ICICIPRULI",
    "selected": true,
    "price": 506.0,
    "change": -0.1,
    "oichange": 0.0,
    "changePrev": 4.15,
    "oichangePrev": 0.0
  },
  {
    "name": "CUB",
    "selected": true,
    "price": 137.85,
    "change": 0.44,
    "oichange": 0.0,
    "changePrev": -2.8,
    "oichangePrev": 0.0
  },
  {
    "name": "TIMKEN",
    "selected": true,
    "price": 3316.6,
    "change": 0.02,
    "oichange": 0.0,
    "changePrev": 0.48,
    "oichangePrev": 0.0
  },
  {
    "name": "SWANENERGY",
    "selected": true,
    "price": 679.4,
    "change": -1.09,
    "oichange": 0.0,
    "changePrev": 12.75,
    "oichangePrev": 0.0
  },
  {
    "name": "LXCHEM",
    "selected": true,
    "price": 261.4,
    "change": -1.62,
    "oichange": 0.0,
    "changePrev": -1.96,
    "oichangePrev": 0.0
  },
  {
    "name": "THERMAX",
    "selected": true,
    "price": 3144.2,
    "change": 1.59,
    "oichange": 0.0,
    "changePrev": -0.65,
    "oichangePrev": 0.0
  },
  {
    "name": "VIPIND",
    "selected": true,
    "price": 539.85,
    "change": 1.49,
    "oichange": 0.0,
    "changePrev": -4.16,
    "oichangePrev": 0.0
  },
  {
    "name": "ASHOKLEY",
    "selected": true,
    "price": 178.35,
    "change": 2.47,
    "oichange": 0.0,
    "changePrev": 2.53,
    "oichangePrev": 0.0
  },
  {
    "name": "ROSSARI",
    "selected": true,
    "price": 774.55,
    "change": -0.93,
    "oichange": 0.0,
    "changePrev": 0.52,
    "oichangePrev": 0.0
  },
  {
    "name": "RATNAMANI",
    "selected": true,
    "price": 3318.4,
    "change": -0.48,
    "oichange": 0.0,
    "changePrev": 4.63,
    "oichangePrev": 0.0
  },
  {
    "name": "GRASIM",
    "selected": true,
    "price": 2114.65,
    "change": -1.16,
    "oichange": 0.0,
    "changePrev": 3.03,
    "oichangePrev": 0.0
  },
  {
    "name": "KNRCON",
    "selected": true,
    "price": 284.6,
    "change": 0.49,
    "oichange": 0.0,
    "changePrev": 7.62,
    "oichangePrev": 0.0
  },
  {
    "name": "SAREGAMA",
    "selected": true,
    "price": 359.1,
    "change": 2.67,
    "oichange": 0.0,
    "changePrev": 0.19,
    "oichangePrev": 0.0
  },
  {
    "name": "M\u0026MFIN",
    "selected": true,
    "price": 286.5,
    "change": -0.33,
    "oichange": 1.05,
    "changePrev": 1.02,
    "oichangePrev": 0.83
  },
  {
    "name": "EMAMILTD",
    "selected": true,
    "price": 506.55,
    "change": 1.02,
    "oichange": 0.0,
    "changePrev": 1.82,
    "oichangePrev": 0.0
  },
  {
    "name": "UPL",
    "selected": true,
    "price": 486.45,
    "change": -8.84,
    "oichange": 0.0,
    "changePrev": -0.68,
    "oichangePrev": 0.0
  },
  {
    "name": "JAMNAAUTO",
    "selected": true,
    "price": 121.5,
    "change": 2.53,
    "oichange": 0.0,
    "changePrev": 6.8,
    "oichangePrev": 0.0
  },
  {
    "name": "SOBHA",
    "selected": true,
    "price": 1416.3,
    "change": 0.13,
    "oichange": 0.0,
    "changePrev": 2.38,
    "oichangePrev": 0.0
  },
  {
    "name": "INDUSTOWER",
    "selected": true,
    "price": 214.85,
    "change": -0.6,
    "oichange": 0.0,
    "changePrev": -4.13,
    "oichangePrev": 0.0
  },
  {
    "name": "KPIL",
    "selected": true,
    "price": 846.7,
    "change": 1.57,
    "oichange": 0.0,
    "changePrev": 11.93,
    "oichangePrev": 0.0
  },
  {
    "name": "GESHIP",
    "selected": true,
    "price": 983.45,
    "change": 1.94,
    "oichange": 0.0,
    "changePrev": -4.26,
    "oichangePrev": 0.0
  },
  {
    "name": "MUTHOOTFIN",
    "selected": true,
    "price": 1379.8,
    "change": 0.17,
    "oichange": 0.0,
    "changePrev": -0.77,
    "oichangePrev": 0.0
  },
  {
    "name": "MTARTECH",
    "selected": true,
    "price": 2005.0,
    "change": -0.86,
    "oichange": 0.0,
    "changePrev": -4.16,
    "oichangePrev": 0.0
  },
  {
    "name": "REDINGTON",
    "selected": true,
    "price": 196.0,
    "change": 3.95,
    "oichange": 0.0,
    "changePrev": 8.99,
    "oichangePrev": 0.0
  },
  {
    "name": "AJANTPHARM",
    "selected": true,
    "price": 2161.85,
    "change": -0.3,
    "oichange": 0.0,
    "changePrev": -0.76,
    "oichangePrev": 0.0
  },
  {
    "name": "ONGC",
    "selected": true,
    "price": 265.6,
    "change": 3.25,
    "oichange": 0.0,
    "changePrev": 9.91,
    "oichangePrev": 0.0
  },
  {
    "name": "AXISBANK",
    "selected": true,
    "price": 1065.7,
    "change": -0.13,
    "oichange": 0.0,
    "changePrev": 2.38,
    "oichangePrev": 0.0
  },
  {
    "name": "ATUL",
    "selected": true,
    "price": 6384.9,
    "change": 0.12,
    "oichange": 0.0,
    "changePrev": 0.8,
    "oichangePrev": 0.0
  },
  {
    "name": "VARROC",
    "selected": true,
    "price": 611.1,
    "change": 1.79,
    "oichange": 0.0,
    "changePrev": 16.72,
    "oichangePrev": 0.0
  },
  {
    "name": "BAJAJHLDNG",
    "selected": true,
    "price": 8451.95,
    "change": -0.11,
    "oichange": 0.0,
    "changePrev": 3.26,
    "oichangePrev": 0.0
  },
  {
    "name": "SKFINDIA",
    "selected": true,
    "price": 4559.85,
    "change": 0.23,
    "oichange": 0.0,
    "changePrev": -1.05,
    "oichangePrev": 0.0
  },
  {
    "name": "ABFRL",
    "selected": true,
    "price": 251.3,
    "change": 1.15,
    "oichange": 0.0,
    "changePrev": 2.84,
    "oichangePrev": 0.0
  },
  {
    "name": "MANYAVAR",
    "selected": true,
    "price": 960.3,
    "change": -0.14,
    "oichange": 0.0,
    "changePrev": -14.52,
    "oichangePrev": 0.0
  },
  {
    "name": "BLUEDART",
    "selected": true,
    "price": 6381.75,
    "change": -0.28,
    "oichange": 0.0,
    "changePrev": -3.3,
    "oichangePrev": 0.0
  },
  {
    "name": "PFIZER",
    "selected": true,
    "price": 4737.15,
    "change": 1.66,
    "oichange": 0.0,
    "changePrev": 8.63,
    "oichangePrev": 0.0
  },
  {
    "name": "LALPATHLAB",
    "selected": true,
    "price": 2462.5,
    "change": 0.38,
    "oichange": 0.0,
    "changePrev": 2.2,
    "oichangePrev": 0.0
  },
  {
    "name": "APTUS",
    "selected": true,
    "price": 370.15,
    "change": 0.03,
    "oichange": 0.0,
    "changePrev": 0.18,
    "oichangePrev": 0.0
  },
  {
    "name": "WESTLIFE",
    "selected": true,
    "price": 836.4,
    "change": -1.21,
    "oichange": 0.0,
    "changePrev": 2.26,
    "oichangePrev": 0.0
  },
  {
    "name": "IDFC",
    "selected": true,
    "price": 118.95,
    "change": 1.02,
    "oichange": 0.0,
    "changePrev": 1.51,
    "oichangePrev": 0.0
  },
  {
    "name": "IOC",
    "selected": true,
    "price": 175.3,
    "change": 7.61,
    "oichange": 0.0,
    "changePrev": 13.36,
    "oichangePrev": 0.0
  },
  {
    "name": "ALKEM",
    "selected": true,
    "price": 5037.45,
    "change": 2.44,
    "oichange": 0.0,
    "changePrev": -1.09,
    "oichangePrev": 0.0
  },
  {
    "name": "FORTIS",
    "selected": true,
    "price": 437.7,
    "change": 1.85,
    "oichange": 0.0,
    "changePrev": -0.09,
    "oichangePrev": 0.0
  },
  {
    "name": "NETWORK18",
    "selected": true,
    "price": 116.0,
    "change": 2.52,
    "oichange": 0.0,
    "changePrev": -6.14,
    "oichangePrev": 0.0
  },
  {
    "name": "CENTRALBK",
    "selected": true,
    "price": 68.4,
    "change": 10.23,
    "oichange": 0.0,
    "changePrev": 14.17,
    "oichangePrev": 0.0
  },
  {
    "name": "CAMPUS",
    "selected": true,
    "price": 260.35,
    "change": -1.51,
    "oichange": 0.0,
    "changePrev": -1.27,
    "oichangePrev": 0.0
  },
  {
    "name": "RHIM",
    "selected": true,
    "price": 720.3,
    "change": -2.07,
    "oichange": 0.0,
    "changePrev": 1.96,
    "oichangePrev": 0.0
  },
  {
    "name": "DATAPATTNS",
    "selected": true,
    "price": 1890.2,
    "change": -1.29,
    "oichange": 0.0,
    "changePrev": 3.06,
    "oichangePrev": 0.0
  },
  {
    "name": "HFCL",
    "selected": true,
    "price": 98.65,
    "change": 1.91,
    "oichange": 0.0,
    "changePrev": -8.46,
    "oichangePrev": 0.0
  },
  {
    "name": "SBICARD",
    "selected": true,
    "price": 703.5,
    "change": -1.09,
    "oichange": 0.0,
    "changePrev": -6.4,
    "oichangePrev": 0.0
  },
  {
    "name": "MPHASIS",
    "selected": true,
    "price": 2508.7,
    "change": -2.01,
    "oichange": 0.0,
    "changePrev": 1.5,
    "oichangePrev": 0.0
  },
  {
    "name": "GOCOLORS",
    "selected": true,
    "price": 1054.9,
    "change": -1.21,
    "oichange": 0.0,
    "changePrev": -4.32,
    "oichangePrev": 0.0
  },
  {
    "name": "ESCORTS",
    "selected": true,
    "price": 2973.9,
    "change": 1.0,
    "oichange": 0.0,
    "changePrev": -0.03,
    "oichangePrev": 0.0
  },
  {
    "name": "PRAJIND",
    "selected": true,
    "price": 474.9,
    "change": -0.49,
    "oichange": 0.0,
    "changePrev": -6.7,
    "oichangePrev": 0.0
  },
  {
    "name": "SUMICHEM",
    "selected": true,
    "price": 400.85,
    "change": 0.2,
    "oichange": 0.0,
    "changePrev": 1.48,
    "oichangePrev": 0.0
  },
  {
    "name": "VGUARD",
    "selected": true,
    "price": 317.25,
    "change": 2.32,
    "oichange": 0.0,
    "changePrev": 5.69,
    "oichangePrev": 0.0
  },
  {
    "name": "BAJAJFINSV",
    "selected": true,
    "price": 1628.15,
    "change": -1.41,
    "oichange": 0.0,
    "changePrev": 1.31,
    "oichangePrev": 0.0
  },
  {
    "name": "MEDANTA",
    "selected": true,
    "price": 1224.3,
    "change": -1.98,
    "oichange": 0.0,
    "changePrev": 12.78,
    "oichangePrev": 0.0
  },
  {
    "name": "PAYTM",
    "selected": true,
    "price": 438.5,
    "change": -10.0,
    "oichange": 0.0,
    "changePrev": -36.15,
    "oichangePrev": 0.0
  },
  {
    "name": "ENDURANCE",
    "selected": true,
    "price": 2145.1,
    "change": 0.75,
    "oichange": 0.0,
    "changePrev": 7.54,
    "oichangePrev": 0.0
  },
  {
    "name": "NUVOCO",
    "selected": true,
    "price": 360.3,
    "change": 0.08,
    "oichange": 0.0,
    "changePrev": 3.63,
    "oichangePrev": 0.0
  },
  {
    "name": "KEC",
    "selected": true,
    "price": 653.85,
    "change": -1.85,
    "oichange": 0.0,
    "changePrev": 8.16,
    "oichangePrev": 0.0
  },
  {
    "name": "AMBUJACEM",
    "selected": true,
    "price": 559.1,
    "change": 0.3,
    "oichange": 0.0,
    "changePrev": -0.49,
    "oichangePrev": 0.0
  },
  {
    "name": "TEJASNET",
    "selected": true,
    "price": 752.8,
    "change": -2.07,
    "oichange": 0.0,
    "changePrev": -0.32,
    "oichangePrev": 0.0
  },
  {
    "name": "HDFCLIFE",
    "selected": true,
    "price": 571.7,
    "change": -1.23,
    "oichange": 0.0,
    "changePrev": -0.03,
    "oichangePrev": 0.0
  },
  {
    "name": "HDFCBANK",
    "selected": true,
    "price": 1446.35,
    "change": 0.01,
    "oichange": 0.0,
    "changePrev": 0.78,
    "oichangePrev": 0.0
  },
  {
    "name": "MAHLIFE",
    "selected": true,
    "price": 620.2,
    "change": 9.3,
    "oichange": 0.0,
    "changePrev": 2.04,
    "oichangePrev": 0.0
  },
  {
    "name": "VMART",
    "selected": true,
    "price": 2101.9,
    "change": 0.82,
    "oichange": 0.0,
    "changePrev": 0.54,
    "oichangePrev": 0.0
  },
  {
    "name": "MEDPLUS",
    "selected": true,
    "price": 680.05,
    "change": -0.94,
    "oichange": 0.0,
    "changePrev": -5.05,
    "oichangePrev": 0.0
  },
  {
    "name": "DABUR",
    "selected": true,
    "price": 538.25,
    "change": -1.18,
    "oichange": 0.0,
    "changePrev": 2.45,
    "oichangePrev": 0.0
  },
  {
    "name": "POLYMED",
    "selected": true,
    "price": 1504.75,
    "change": -1.01,
    "oichange": 0.0,
    "changePrev": 6.68,
    "oichangePrev": 0.0
  },
  {
    "name": "TVSMOTOR",
    "selected": true,
    "price": 2033.05,
    "change": -0.6,
    "oichange": 0.0,
    "changePrev": 5.37,
    "oichangePrev": 0.0
  },
  {
    "name": "JUBLFOOD",
    "selected": true,
    "price": 493.8,
    "change": -0.21,
    "oichange": 0.0,
    "changePrev": -2.64,
    "oichangePrev": 0.0
  },
  {
    "name": "ASIANPAINT",
    "selected": true,
    "price": 2947.65,
    "change": 0.39,
    "oichange": 0.0,
    "changePrev": -0.44,
    "oichangePrev": 0.0
  },
  {
    "name": "GLAXO",
    "selected": true,
    "price": 2460.75,
    "change": 6.64,
    "oichange": 0.0,
    "changePrev": 5.21,
    "oichangePrev": 0.0
  },
  {
    "name": "DALBHARAT",
    "selected": true,
    "price": 2226.95,
    "change": -1.42,
    "oichange": 0.0,
    "changePrev": 2.45,
    "oichangePrev": 0.0
  },
  {
    "name": "GODREJCP",
    "selected": true,
    "price": 1219.15,
    "change": -1.43,
    "oichange": 0.0,
    "changePrev": 6.87,
    "oichangePrev": 0.0
  },
  {
    "name": "BIKAJI",
    "selected": true,
    "price": 556.55,
    "change": 1.64,
    "oichange": 0.0,
    "changePrev": -4.57,
    "oichangePrev": 0.0
  },
  {
    "name": "RBLBANK",
    "selected": true,
    "price": 270.55,
    "change": 2.17,
    "oichange": 0.0,
    "changePrev": 3.78,
    "oichangePrev": 0.0
  },
  {
    "name": "BRITANNIA",
    "selected": true,
    "price": 5130.2,
    "change": -0.36,
    "oichange": 0.0,
    "changePrev": 0.14,
    "oichangePrev": 0.0
  },
  {
    "name": "L\u0026TFH",
    "selected": true,
    "price": 176.5,
    "change": 1.03,
    "oichange": 0.0,
    "changePrev": 4.67,
    "oichangePrev": 0.0
  },
  {
    "name": "DCMSHRIRAM",
    "selected": true,
    "price": 1023.45,
    "change": 0.74,
    "oichange": 0.0,
    "changePrev": 1.69,
    "oichangePrev": 0.0
  },
  {
    "name": "BALAMINES",
    "selected": true,
    "price": 2291.45,
    "change": -1.51,
    "oichange": 0.0,
    "changePrev": -1.68,
    "oichangePrev": 0.0
  },
  {
    "name": "PVRINOX",
    "selected": true,
    "price": 1430.3,
    "change": -0.29,
    "oichange": 0.0,
    "changePrev": -1.66,
    "oichangePrev": 0.0
  },
  {
    "name": "HEG",
    "selected": true,
    "price": 1919.6,
    "change": 7.6,
    "oichange": 0.0,
    "changePrev": 3.13,
    "oichangePrev": 0.0
  },
  {
    "name": "MMTC",
    "selected": true,
    "price": 92.55,
    "change": 9.98,
    "oichange": 0.0,
    "changePrev": 11.75,
    "oichangePrev": 0.0
  },
  {
    "name": "SAPPHIRE",
    "selected": true,
    "price": 1401.0,
    "change": -0.89,
    "oichange": 0.0,
    "changePrev": -0.79,
    "oichangePrev": 0.0
  },
  {
    "name": "USHAMART",
    "selected": true,
    "price": 364.65,
    "change": 1.52,
    "oichange": 0.0,
    "changePrev": 1.61,
    "oichangePrev": 0.0
  },
  {
    "name": "BATAINDIA",
    "selected": true,
    "price": 1438.15,
    "change": -0.98,
    "oichange": 0.0,
    "changePrev": 0.21,
    "oichangePrev": 0.0
  },
  {
    "name": "RECLTD",
    "selected": true,
    "price": 503.3,
    "change": 1.29,
    "oichange": 0.0,
    "changePrev": 5.69,
    "oichangePrev": 0.0
  },
  {
    "name": "POLYPLEX",
    "selected": true,
    "price": 992.75,
    "change": -1.42,
    "oichange": 0.0,
    "changePrev": -0.91,
    "oichangePrev": 0.0
  },
  {
    "name": "TRITURBINE",
    "selected": true,
    "price": 369.0,
    "change": 0.49,
    "oichange": 0.0,
    "changePrev": -4.82,
    "oichangePrev": 0.0
  },
  {
    "name": "ARE\u0026M",
    "selected": true,
    "price": 901.9,
    "change": 0.74,
    "oichange": 0.0,
    "changePrev": 10.11,
    "oichangePrev": 0.0
  },
  {
    "name": "RBA",
    "selected": true,
    "price": 114.6,
    "change": -1.21,
    "oichange": 0.0,
    "changePrev": -1.32,
    "oichangePrev": 0.0
  },
  {
    "name": "DELHIVERY",
    "selected": true,
    "price": 463.5,
    "change": -2.04,
    "oichange": 0.0,
    "changePrev": 17.9,
    "oichangePrev": 0.0
  },
  {
    "name": "SHRIRAMFIN",
    "selected": true,
    "price": 2388.8,
    "change": -0.69,
    "oichange": 0.0,
    "changePrev": 4.26,
    "oichangePrev": 0.0
  },
  {
    "name": "IDFCFIRSTB",
    "selected": true,
    "price": 83.2,
    "change": 0.79,
    "oichange": 0.0,
    "changePrev": 3.12,
    "oichangePrev": 0.0
  },
  {
    "name": "RAIN",
    "selected": true,
    "price": 187.9,
    "change": 4.48,
    "oichange": 0.0,
    "changePrev": 2.42,
    "oichangePrev": 0.0
  },
  {
    "name": "CRAFTSMAN",
    "selected": true,
    "price": 4228.8,
    "change": -0.57,
    "oichange": 0.0,
    "changePrev": -10.44,
    "oichangePrev": 0.0
  },
  {
    "name": "ASAHIINDIA",
    "selected": true,
    "price": 525.0,
    "change": 0.35,
    "oichange": 0.0,
    "changePrev": -8.15,
    "oichangePrev": 0.0
  },
  {
    "name": "INDIANB",
    "selected": true,
    "price": 559.1,
    "change": 2.41,
    "oichange": 0.0,
    "changePrev": 18.53,
    "oichangePrev": 0.0
  },
  {
    "name": "ANGELONE",
    "selected": true,
    "price": 3276.95,
    "change": -1.84,
    "oichange": 0.0,
    "changePrev": 14.28,
    "oichangePrev": 0.0
  },
  {
    "name": "ACC",
    "selected": true,
    "price": 2498.55,
    "change": -0.04,
    "oichange": 0.0,
    "changePrev": 1.29,
    "oichangePrev": 0.0
  },
  {
    "name": "LAXMIMACH",
    "selected": true,
    "price": 13676.9,
    "change": -0.5,
    "oichange": 0.0,
    "changePrev": 4.22,
    "oichangePrev": 0.0
  },
  {
    "name": "ZENSARTECH",
    "selected": true,
    "price": 562.55,
    "change": 0.29,
    "oichange": 0.0,
    "changePrev": -2.6,
    "oichangePrev": 0.0
  },
  {
    "name": "CLEAN",
    "selected": true,
    "price": 1409.8,
    "change": -3.53,
    "oichange": 0.0,
    "changePrev": 1.35,
    "oichangePrev": 0.0
  },
  {
    "name": "NLCINDIA",
    "selected": true,
    "price": 283.9,
    "change": 6.89,
    "oichange": 0.0,
    "changePrev": 10.76,
    "oichangePrev": 0.0
  },
  {
    "name": "MANAPPURAM",
    "selected": true,
    "price": 185.8,
    "change": -0.08,
    "oichange": 0.0,
    "changePrev": 4.47,
    "oichangePrev": 0.0
  },
  {
    "name": "ZYDUSWELL",
    "selected": true,
    "price": 1594.55,
    "change": -0.26,
    "oichange": 0.0,
    "changePrev": -0.19,
    "oichangePrev": 0.0
  },
  {
    "name": "SUPREMEIND",
    "selected": true,
    "price": 4165.0,
    "change": 0.66,
    "oichange": 0.0,
    "changePrev": 3.06,
    "oichangePrev": 0.0
  },
  {
    "name": "GODREJIND",
    "selected": true,
    "price": 876.9,
    "change": 0.35,
    "oichange": 0.0,
    "changePrev": 3.35,
    "oichangePrev": 0.0
  },
  {
    "name": "DEEPAKFERT",
    "selected": true,
    "price": 554.0,
    "change": -3.49,
    "oichange": 0.0,
    "changePrev": -9.94,
    "oichangePrev": 0.0
  },
  {
    "name": "SUNDARMFIN",
    "selected": true,
    "price": 3708.45,
    "change": 2.73,
    "oichange": 0.0,
    "changePrev": 1.76,
    "oichangePrev": 0.0
  },
  {
    "name": "RALLIS",
    "selected": true,
    "price": 253.9,
    "change": -0.35,
    "oichange": 0.0,
    "changePrev": -1.09,
    "oichangePrev": 0.0
  },
  {
    "name": "TV18BRDCST",
    "selected": true,
    "price": 61.8,
    "change": -0.56,
    "oichange": 0.0,
    "changePrev": -3.27,
    "oichangePrev": 0.0
  },
  {
    "name": "ACI",
    "selected": true,
    "price": 627.2,
    "change": 1.25,
    "oichange": 0.0,
    "changePrev": -0.35,
    "oichangePrev": 0.0
  },
  {
    "name": "GAEL",
    "selected": true,
    "price": 394.85,
    "change": -0.75,
    "oichange": 0.0,
    "changePrev": 8.14,
    "oichangePrev": 0.0
  },
  {
    "name": "APARINDS",
    "selected": true,
    "price": 6059.45,
    "change": -4.18,
    "oichange": 0.0,
    "changePrev": 15.69,
    "oichangePrev": 0.0
  },
  {
    "name": "COLPAL",
    "selected": true,
    "price": 2534.25,
    "change": -0.3,
    "oichange": 0.0,
    "changePrev": 1.97,
    "oichangePrev": 0.0
  },
  {
    "name": "FLUOROCHEM",
    "selected": true,
    "price": 3607.05,
    "change": 1.53,
    "oichange": 0.0,
    "changePrev": -0.47,
    "oichangePrev": 0.0
  },
  {
    "name": "INDIAMART",
    "selected": true,
    "price": 2596.75,
    "change": 1.35,
    "oichange": 0.0,
    "changePrev": 4.61,
    "oichangePrev": 0.0
  },
  {
    "name": "GMRINFRA",
    "selected": true,
    "price": 88.2,
    "change": 3.52,
    "oichange": 0.0,
    "changePrev": 10.58,
    "oichangePrev": 0.0
  },
  {
    "name": "ANURAS",
    "selected": true,
    "price": 933.9,
    "change": -1.73,
    "oichange": 0.0,
    "changePrev": -1.47,
    "oichangePrev": 0.0
  },
  {
    "name": "KEI",
    "selected": true,
    "price": 3177.85,
    "change": -0.72,
    "oichange": 0.0,
    "changePrev": 0.56,
    "oichangePrev": 0.0
  },
  {
    "name": "VAIBHAVGBL",
    "selected": true,
    "price": 481.0,
    "change": 0.0,
    "oichange": 0.0,
    "changePrev": -6.47,
    "oichangePrev": 0.0
  },
  {
    "name": "UBL",
    "selected": true,
    "price": 1775.6,
    "change": -3.84,
    "oichange": 0.0,
    "changePrev": 0.23,
    "oichangePrev": 0.0
  },
  {
    "name": "COROMANDEL",
    "selected": true,
    "price": 1095.0,
    "change": 1.72,
    "oichange": 0.0,
    "changePrev": -4.65,
    "oichangePrev": 0.0
  },
  {
    "name": "CSBBANK",
    "selected": true,
    "price": 384.0,
    "change": -2.23,
    "oichange": 0.0,
    "changePrev": 4.96,
    "oichangePrev": 0.0
  },
  {
    "name": "KSB",
    "selected": true,
    "price": 3678.65,
    "change": 1.36,
    "oichange": 0.0,
    "changePrev": 5.13,
    "oichangePrev": 0.0
  },
  {
    "name": "METROBRAND",
    "selected": true,
    "price": 1057.2,
    "change": -2.33,
    "oichange": 0.0,
    "changePrev": -8.26,
    "oichangePrev": 0.0
  },
  {
    "name": "MCX",
    "selected": true,
    "price": 3877.05,
    "change": 6.07,
    "oichange": 0.0,
    "changePrev": 13.47,
    "oichangePrev": 0.0
  },
  {
    "name": "IBULHSGFIN",
    "selected": true,
    "price": 189.0,
    "change": -0.29,
    "oichange": 0.0,
    "changePrev": -4.53,
    "oichangePrev": 0.0
  },
  {
    "name": "PFC",
    "selected": true,
    "price": 459.55,
    "change": 1.94,
    "oichange": 0.0,
    "changePrev": 7.59,
    "oichangePrev": 0.0
  },
  {
    "name": "NAVINFLUOR",
    "selected": true,
    "price": 3269.9,
    "change": -1.66,
    "oichange": 0.0,
    "changePrev": -0.58,
    "oichangePrev": 0.0
  },
  {
    "name": "AUBANK",
    "selected": true,
    "price": 623.4,
    "change": -0.89,
    "oichange": 0.0,
    "changePrev": -11.14,
    "oichangePrev": 0.0
  },
  {
    "name": "PAGEIND",
    "selected": true,
    "price": 37073.7,
    "change": 0.25,
    "oichange": 0.0,
    "changePrev": 0.73,
    "oichangePrev": 0.0
  },
  {
    "name": "JKLAKSHMI",
    "selected": true,
    "price": 932.4,
    "change": 1.4,
    "oichange": 0.0,
    "changePrev": -1.22,
    "oichangePrev": 0.0
  },
  {
    "name": "RTNINDIA",
    "selected": true,
    "price": 90.3,
    "change": 1.92,
    "oichange": 0.0,
    "changePrev": 9.86,
    "oichangePrev": 0.0
  },
  {
    "name": "SRF",
    "selected": true,
    "price": 2286.05,
    "change": -1.41,
    "oichange": 0.0,
    "changePrev": 2.19,
    "oichangePrev": 0.0
  },
  {
    "name": "WELCORP",
    "selected": true,
    "price": 605.7,
    "change": 2.52,
    "oichange": 0.0,
    "changePrev": 2.07,
    "oichangePrev": 0.0
  },
  {
    "name": "CGCL",
    "selected": true,
    "price": 940.1,
    "change": -2.71,
    "oichange": 0.0,
    "changePrev": 2.75,
    "oichangePrev": 0.0
  },
  {
    "name": "GILLETTE",
    "selected": true,
    "price": 6607.5,
    "change": 0.62,
    "oichange": 0.0,
    "changePrev": 0.93,
    "oichangePrev": 0.0
  },
  {
    "name": "NESTLEIND",
    "selected": true,
    "price": 2485.85,
    "change": 0.18,
    "oichange": 0.0,
    "changePrev": -0.03,
    "oichangePrev": 0.0
  },
  {
    "name": "IDEA",
    "selected": true,
    "price": 13.9,
    "change": -1.07,
    "oichange": 0.0,
    "changePrev": -3.77,
    "oichangePrev": 0.0
  },
  {
    "name": "ALLCARGO",
    "selected": true,
    "price": 80.35,
    "change": 1.32,
    "oichange": 0.0,
    "changePrev": -0.69,
    "oichangePrev": 0.0
  },
  {
    "name": "ZEEL",
    "selected": true,
    "price": 176.55,
    "change": 2.11,
    "oichange": 0.0,
    "changePrev": 5.94,
    "oichangePrev": 0.0
  }
]