[
  {
    "symbol": "ITC",
    "interval": "1d",
    "strategy": "ChartShortStrategy",
    "entryType": "SELL",
    "exitType": "CLOSED",
    "entryDate": 1690279200,
    "exitDate": 1701770400,
    "profit": 2.28,
    "entryPrice": 462.3,
    "exitPrice": 451.75
  },
  {
    "symbol": "IDFCFIRSTB",
    "interval": "1d",
    "strategy": "ChartLongStrategy",
    "entryType": "BUY",
    "exitType": "OPEN",
    "entryDate": 1701770400,
    "exitDate": 1704448800,
    "profit": -2.86,
    "entryPrice": 89.25,
    "exitPrice": 86.7
  },
  {
    "symbol": "BAJAJ-AUTO",
    "interval": "1d",
    "strategy": "ChartShortStrategy",
    "entryType": "SELL",
    "exitType": "OPEN",
    "entryDate": 1701941100,
    "exitDate": 1704448800,
    "profit": -14.77,
    "entryPrice": 6080.55,
    "exitPrice": 6978.5
  },
  {
    "symbol": "LALPATHLAB",
    "interval": "1d",
    "strategy": "ChartShortStrategy",
    "entryType": "SELL",
    "exitType": "OPEN",
    "entryDate": 1702029000,
    "exitDate": 1704448800,
    "profit": 1.63,
    "entryPrice": 2640.55,
    "exitPrice": 2597.6
  },
  {
    "symbol": "ABCAPITAL",
    "interval": "1d",
    "strategy": "ChartShortStrategy",
    "entryType": "SELL",
    "exitType": "OPEN",
    "entryDate": 1702029600,
    "exitDate": 1704448800,
    "profit": -7.29,
    "entryPrice": 163.2,
    "exitPrice": 175.1
  },
  {
    "symbol": "RBLBANK",
    "interval": "1d",
    "strategy": "ChartLongStrategy",
    "entryType": "BUY",
    "exitType": "OPEN",
    "entryDate": 1702029600,
    "exitDate": 1704448800,
    "profit": 7.4,
    "entryPrice": 267.7,
    "exitPrice": 287.5
  },
  {
    "symbol": "ADANIENT",
    "interval": "1d",
    "strategy": "ChartLongStrategy",
    "entryType": "BUY",
    "exitType": "OPEN",
    "entryDate": 1702029600,
    "exitDate": 1704448800,
    "profit": 6.54,
    "entryPrice": 2822.15,
    "exitPrice": 3006.6
  },
  {
    "symbol": "PIIND",
    "interval": "1d",
    "strategy": "ChartShortStrategy",
    "entryType": "SELL",
    "exitType": "OPEN",
    "entryDate": 1702461600,
    "exitDate": 1704448800,
    "profit": -0.98,
    "entryPrice": 3426.85,
    "exitPrice": 3460.5
  }
]